Workbook
Name Slicer_Branch: #N/A
Name Slicer_Clean_City: #N/A
Name Slicer_Clean_payment_Method: #N/A
Name Slicer_Clean_Product_Name: #N/A

Sheet RAW DATA
A1: Transaction_ID | B1: Date | C1: Customer_ID | D1: Customer_Name | E1: Gender | F1: Age | G1: City | H1: Product_Category | I1: Product_Name | J1: Unit_Price | K1: Quantity | L1: Discount (%) | M1: Payment_Method | N1: Salesperson | O1: Branch | P1: Customer_Rating
A2: T100002 | B2: 2025-10-06 | C2: C9114 | D2: Peter | E2: Male | F2: 130 | G2: lagos | H2: Fashion | I2: Shirt | J2: 237.91 | K2: -2 | L2: -10 | M2: POS | N2: Dan | O2: North | P2: 4
A3: T100003 | B3: 2025-02-22 | C3: C7218 | D3: Peter | E3: Male | F3: 22 | G3: LAGOS | H3: Sports | I3: Ball | J3: 103.48 | K3: -2 | L3: 0 | N3: Dan | O3: West | P3: 4
A4: T100004 | B4: 2026-04-20 | C4: C9957 | D4: Aisha | E4: Male | F4: 55 | G4: PH | H4: Electronics | I4: Phone | J4: 436.14 | K4: -2 | L4: 10 | M4: POS | N4: Chi | O4: West
A5: T100005 | B5: 2026-02-21 | C5: C1077 | D5: James | E5: Female | F5: 130 | G5: Enugu | H5: Groceries | I5: Rice | J5: 430.25 | K5: -2 | L5: 10 | N5: Chi | O5: West | P5: 2
A6: T100006 | B6: 2025-10-13 | C6: C6441 | E6: Female | F6: 37 | G6: Lagos | H6: Home | I6: Chair | J6: 44.01 | K6: -2 | L6: 120 | M6: POS | N6: Dan | O6: West | P6: 4
A7: T100007 | B7: 10/11/2025 | C7: C6943 | D7: Aisha | E7: Female | F7: 130 | G7: Lagos | H7: Sports | I7: Ball | J7: 356.22 | K7: -2 | L7: 5 | M7: Mobile Money | N7: Chi | O7: West | P7: 1
A8: T100008 | B8: 2025-08-17 | C8: C1101 | D8: John | E8: Female | F8: 8 | G8: Enugu | H8: Electronics | I8: Phone | J8: 323.16 | K8: 4 | L8: 120 | M8: Transfer | N8: Chi | O8: South
A9: T100009 | B9: 2025-04-07 | C9: C8179 | D9: Mary | E9: Female | F9: 30 | G9: Abuja | H9: Sports | I9: Ball | J9: 126.25 | K9: 7 | L9: 0 | N9: Dan | O9: West | P9: 4
A10: T100010 | B10: 2025-04-01 | C10: C2862 | D10: Aisha | E10: Male | F10: 8 | G10: Abuja | H10: Sports | I10: Ball | J10: 233.45 | K10: 8 | L10: 10 | N10: Chi | O10: North | P10: 1
A11: T100011 | B11: 2025-09-10 | C11: C4724 | D11: Peter | E11: Female | F11: 8 | G11: PH | H11: Electronics | I11: Phone | J11: 150.57 | K11: -2 | L11: 10 | M11: Cash | N11: Chi | O11: West | P11: 4
A12: T100012 | B12: 2025-02-07 | C12: C2129 | D12: James | E12: Female | F12: 8 | G12: Lagos | H12: Fashion | I12: Shirt | J12: 49.62 | K12: 7 | L12: 120 | M12: Mobile Money | N12: Ada | O12: East | P12: 4
A13: T100013 | B13: 2025-06-09 | C13: C4291 | D13: Peter | E13: Male | F13: 130 | G13: Kano | H13: groceris | I13: Rice | J13: 409.19 | K13: -2 | L13: 120 | M13: POS | N13: Ada | O13: West | P13: 5
A14: T100014 | B14: 12/04/2025 | C14: C1596 | D14: John | E14: Male | F14: 130 | G14: Kano | H14: Home | I14: Chair | J14: 126.04 | K14: -2 | L14: 15 | M14: Transfer | N14: Ben | O14: South | P14: 4
A15: T100015 | B15: 2025-10-21 | C15: C1752 | D15: Aisha | E15: Female | F15: 130 | G15: Lagos | H15: Groceries | I15: Rice | J15: 477.09 | K15: -2 | L15: 0 | M15: Mobile Money | N15: Dan | O15: East | P15: 4
A16: T100016 | B16: 2025-05-25 | C16: C5577 | D16: Mary | E16: Male | F16: 130 | G16: Lagos | H16: groceris | I16: Rice | J16: 332 | K16: -2 | L16: 5 | M16: Transfer | N16: Dan | O16: East | P16: 4
A17: T100017 | B17: 2025-01-24 | C17: C8070 | D17: Grace | E17: Male | F17: 28 | G17: Lagos | H17: groceris | I17: Rice | J17: 484.12 | K17: 1 | L17: -10 | M17: POS | N17: Dan | O17: North | P17: 2
A18: T100018 | B18: 2026-02-22 | C18: C3714 | E18: Female | F18: 8 | G18: Kano | H18: groceris | I18: Rice | J18: 487.9 | K18: 6 | L18: -10 | M18: Transfer | N18: Ada | O18: South | P18: 2
A19: T100019 | B19: 2025-07-11 | C19: C4372 | D19: Peter | E19: Female | F19: 43 | G19: Abuja | H19: Sports | I19: Ball | J19: 398.62 | K19: -2 | L19: 10 | N19: Ben | O19: West | P19: 1
A20: T100020 | B20: 2026-02-25 | C20: C1826 | D20: Mary | E20: Male | F20: 130 | G20: Kano | H20: groceris | I20: Rice | J20: 68.67 | K20: 4 | L20: 10 | N20: Ben | O20: West
A21: T100021 | B21: 02/07/2025 | C21: C8532 | D21: John | E21: Male | F21: 8 | G21: Abuja | H21: Fashion | I21: Shirt | J21: 477.46 | K21: -2 | L21: -10 | M21: Cash | N21: Ada | O21: West | P21: 2
A22: T100022 | B22: 2025-10-19 | C22: C1462 | D22: David | E22: Male | F22: 130 | G22: Enugu | H22: Sports | I22: Ball | J22: 29.5 | K22: -2 | L22: 120 | M22: Cash | N22: Dan | O22: South | P22: 3
A23: T100023 | B23: 2025-08-16 | C23: C6481 | D23: James | E23: Male | F23: 8 | G23: lagos | H23: Beauty | I23: Cream | J23: 134.08 | K23: 5 | L23: 0 | N23: Ben | O23: South | P23: 2
A24: T100024 | B24: 2025-09-24 | C24: C2962 | D24: Grace | E24: Female | F24: 130 | G24: Abuja | H24: Fashion | I24: Shirt | J24: 388.4 | K24: -2 | L24: 15 | M24: Mobile Money | N24: Ada | O24: North | P24: 1
A25: T100025 | B25: 2025-06-10 | C25: C3575 | D25: James | E25: Female | F25: 130 | G25: Kano | H25: Fashion | I25: Shirt | J25: 279.11 | K25: -2 | L25: 10 | M25: Transfer | N25: Ben | O25: West
A26: T100026 | B26: 2025-05-26 | C26: C5211 | D26: David | E26: Male | F26: 130 | G26: Abuja | H26: Beauty | I26: Cream | J26: 205.37 | K26: -2 | L26: -10 | M26: Cash | N26: Ada | O26: North
A27: T100027 | B27: 2025-05-27 | C27: C5215 | D27: Aisha | E27: Female | F27: 58 | G27: PH | H27: groceris | I27: Rice | J27: 72.55 | K27: 6 | L27: 15 | M27: Mobile Money | N27: Ben | O27: East | P27: 1
A28: T100028 | B28: 07/01/2025 | C28: C8821 | D28: Mary | E28: Female | F28: 130 | G28: lagos | H28: groceris | I28: Rice | J28: 275.95 | K28: -2 | L28: 10 | N28: Dan | O28: West | P28: 3
A29: T100029 | B29: 2025-10-19 | C29: C2182 | D29: Aisha | E29: Female | F29: 8 | G29: Enugu | H29: Beauty | I29: Cream | J29: 161.33 | K29: 4 | L29: 10 | M29: Cash | N29: Ben | O29: East | P29: 3
A30: T100030 | B30: 2026-01-06 | C30: C5052 | E30: Female | F30: 58 | G30: Lagos | H30: Beauty | I30: Cream | J30: 416.14 | K30: 10 | L30: 120 | M30: Mobile Money | N30: Ada | O30: North | P30: 1
A31: T100031 | B31: 2026-02-16 | C31: C6457 | D31: John | E31: Male | F31: 8 | G31: PH | H31: groceris | I31: Rice | J31: 258.57 | K31: 2 | L31: -10 | M31: POS | N31: Ben | O31: West | P31: 3
A32: T100032 | B32: 2025-03-23 | C32: C8802 | D32: John | E32: Male | F32: 130 | G32: LAGOS | H32: Sports | I32: Ball | J32: 395.37 | K32: -2 | L32: 5 | M32: Mobile Money | N32: Ada | O32: South | P32: 4
A33: T100033 | B33: 2025-10-09 | C33: C7652 | D33: Aisha | E33: Male | F33: 37 | G33: Kano | H33: Sports | I33: Ball | J33: 429.08 | K33: 9 | L33: 0 | M33: Mobile Money | N33: Chi | O33: East | P33: 4
A34: T100034 | B34: 2025-07-11 | C34: C9293 | D34: David | E34: Female | F34: 35 | G34: Enugu | H34: groceris | I34: Rice | J34: 467.61 | K34: -2 | L34: 120 | M34: Transfer | N34: Chi | O34: East | P34: 4
A35: T100035 | B35: 13/03/2026 | C35: C2683 | D35: Mary | E35: Female | F35: 130 | G35: PH | H35: Beauty | I35: Cream | J35: 402.37 | K35: 10 | L35: 0 | M35: Transfer | N35: Dan | O35: South | P35: 4
A36: T100036 | B36: 2025-12-30 | C36: C1794 | D36: Grace | E36: Male | F36: 19 | G36: LAGOS | H36: Home | I36: Chair | J36: 489.41 | K36: 1 | L36: 0 | M36: Transfer | N36: Chi | O36: South | P36: 3
A37: T100037 | B37: 2025-11-16 | C37: C3074 | D37: John | E37: Female | F37: 64 | G37: LAGOS | H37: Fashion | I37: Shirt | J37: 203.77 | K37: 9 | L37: 120 | M37: Transfer | N37: Chi | O37: South | P37: 3
A38: T100038 | B38: 2025-07-10 | C38: C2121 | D38: James | E38: Female | F38: 8 | G38: PH | H38: Sports | I38: Ball | J38: 333.17 | K38: 8 | L38: -10 | M38: Cash | N38: Ada | O38: South | P38: 4
A39: T100039 | B39: 2025-12-11 | C39: C5675 | D39: John | E39: Female | F39: 130 | G39: Kano | H39: Home | I39: Chair | J39: 166.86 | K39: -2 | L39: 5 | M39: Mobile Money | N39: Chi | O39: South | P39: 3
A40: T100040 | B40: 2025-01-28 | C40: C5040 | D40: John | E40: Female | F40: 19 | G40: Kano | H40: Beauty | I40: Cream | J40: 442.23 | K40: -2 | L40: 120 | M40: POS | N40: Chi | O40: South | P40: 1
A41: T100041 | B41: 2025-10-13 | C41: C4744 | D41: James | E41: Male | F41: 8 | G41: Kano | H41: groceris | I41: Rice | J41: 189.02 | K41: 7 | L41: 5 | M41: Mobile Money | N41: Ben | O41: West | P41: 2
A42: T100042 | B42: 25/11/2025 | C42: C8128 | D42: David | E42: Male | F42: 55 | G42: Abuja | H42: groceris | I42: Rice | J42: 393.19 | K42: 3 | L42: -10 | M42: Cash | N42: Ben | O42: West | P42: 5
... A46: T100046 | B46: 2025-06-23 | C46: C5447 | D46: James | E46: Male | F46: 8 | G46: Kano | H46: Fashion | I46: Shirt | J46: 208.01 | K46: -2 | L46: 120 | M46: Mobile Money | N46: Chi | O46: North | P46: 3
A47: T100047 | B47: 2025-12-09 | C47: C4617 | D47: Aisha | E47: Female | F47: 35 | G47: LAGOS | H47: Fashion | I47: Shirt | J47: 81.69 | K47: 5 | L47: 10 | N47: Chi | O47: South | P47: 5
A48: T100048 | B48: 2025-08-10 | C48: C8875 | D48: Peter | E48: Female | F48: 31 | G48: Enugu | H48: Fashion | I48: Shirt | J48: 259.49 | K48: 10 | L48: 5 | M48: POS | N48: Dan | O48: North
A49: T100049 | B49: 08/03/2025 | C49: C9888 | D49: Aisha | E49: Female | F49: 130 | G49: Lagos | H49: Fashion | I49: Shirt | J49: 314.5 | K49: -2 | L49: 0 | M49: Transfer | N49: Ada | O49: West | P49: 1
A50: T100050 | B50: 2026-05-13 | C50: C1503 | D50: Aisha | E50: Female | F50: 43 | G50: LAGOS | H50: Beauty | I50: Cream | J50: 55.24 | K50: -2 | L50: 10 | N50: Dan | O50: West | P50: 4
A51: T100051 | B51: 2025-10-08 | C51: C3078 | D51: Mary | E51: Male | F51: 8 | G51: Lagos | H51: Sports | I51: Ball | J51: 69.56 | K51: -2 | L51: 0 | M51: POS | N51: Ben | O51: East | P51: 4
A52: T100052 | B52: 2026-01-16 | C52: C5288 | D52: David | E52: Female | F52: 38 | G52: lagos | H52: Electronics | I52: Phone | J52: 251.91 | K52: 2 | L52: -10 | M52: POS | N52: Dan | O52: North | P52: 2
A53: T100053 | B53: 2025-06-13 | C53: C6608 | D53: James | E53: Male | F53: 130 | G53: Lagos | H53: groceris | I53: Rice | J53: 45.83 | K53: 10 | L53: 5 | N53: Chi | O53: East | P53: 5
A54: T100054 | B54: 2025-07-03 | C54: C4525 | E54: Male | F54: 130 | G54: lagos | H54: Sports | I54: Ball | J54: 296.27 | K54: -2 | L54: 10 | M54: Transfer | N54: Ada | O54: West | P54: 3
A55: T100055 | B55: 2025-01-11 | C55: C7424 | D55: Peter | E55: Female | F55: 8 | G55: Kano | H55: Home | I55: Chair | J55: 5.33 | K55: -2 | L55: -10 | M55: Cash | N55: Ben | O55: South | P55: 4
A56: T100056 | B56: 14/05/2026 | C56: C2827 | E56: Female | F56: 8 | G56: LAGOS | H56: groceris | I56: Rice | J56: 280.75 | K56: -2 | L56: 5 | M56: Transfer | N56: Ben | O56: East | P56: 3
A57: T100057 | B57: 2025-04-17 | C57: C1406 | D57: David | E57: Male | F57: 50 | G57: lagos | H57: Sports | I57: Ball | J57: 14.25 | K57: 7 | L57: 5 | M57: Mobile Money | N57: Dan | O57: West | P57: 3
A58: T100058 | B58: 2025-06-19 | C58: C5616 | D58: John | E58: Male | F58: 43 | G58: Abuja | H58: Fashion | I58: Shirt | J58: 372.98 | K58: -2 | L58: 15 | M58: POS | N58: Dan | O58: South
A59: T100059 | B59: 2025-04-08 | C59: C3581 | D59: Grace | E59: Male | F59: 8 | G59: Lagos | H59: groceris | I59: Rice | J59: 98.86 | K59: 9 | L59: 120 | M59: POS | N59: Dan | O59: North | P59: 5
A60: T100060 | B60: 2026-04-17 | C60: C7298 | D60: James | E60: Male | F60: 8 | G60: Lagos | H60: Groceries | I60: Rice | J60: 481.05 | K60: 2 | L60: 0 | N60: Chi | O60: North | P60: 1
A61: T100061 | B61: 2026-05-21 | C61: C2137 | E61: Male | F61: 41 | G61: lagos | H61: groceris | I61: Rice | J61: 172.45 | K61: -2 | L61: 10 | M61: Transfer | N61: Dan | O61: East | P61: 1
A62: T100062 | B62: 2025-11-28 | C62: C5849 | E62: Female | F62: 52 | G62: lagos | H62: Beauty | I62: Cream | J62: 308.43 | K62: -2 | L62: 5 | M62: Cash | N62: Ben | O62: West | P62: 3
A63: T100063 | B63: 02/07/2025 | C63: C7933 | D63: Mary | E63: Male | F63: 29 | G63: Enugu | H63: Electronics | I63: Phone | J63: 239.81 | K63: 10 | L63: 15 | M63: Transfer | N63: Ada | O63: East | P63: 4
A64: T100064 | B64: 2025-06-16 | C64: C3249 | D64: James | E64: Female | F64: 43 | G64: PH | H64: Home | I64: Chair | J64: 12.92 | K64: 10 | L64: 10 | M64: Transfer | N64: Dan | O64: West | P64: 4
A65: T100065 | B65: 2025-07-21 | C65: C3400 | E65: Male | F65: 130 | G65: Abuja | H65: Home | I65: Chair | J65: 381.75 | K65: -2 | L65: 5 | N65: Ben | O65: West
A66: T100066 | B66: 2025-06-20 | C66: C7913 | D66: Aisha | E66: Female | F66: 54 | G66: lagos | H66: groceris | I66: Rice | J66: 481.13 | K66: 7 | L66: 15 | M66: Cash | N66: Ada | O66: South | P66: 4
A67: T100067 | B67: 2026-06-23 | C67: C2685 | D67: Grace | E67: Female | F67: 130 | G67: lagos | H67: Fashion | I67: Shirt | J67: 141.11 | K67: -2 | L67: 0 | M67: Cash | N67: Dan | O67: South
A68: T100068 | B68: 2026-01-19 | C68: C6284 | D68: John | E68: Male | F68: 29 | G68: PH | H68: groceris | I68: Rice | J68: 137.34 | K68: 10 | L68: 5 | M68: POS | N68: Ada | O68: East | P68: 3
A69: T100069 | B69: 2026-06-03 | C69: C5459 | D69: Grace | E69: Female | F69: 130 | G69: Lagos | H69: groceris | I69: Rice | J69: 223.18 | K69: -2 | L69: -10 | M69: Transfer | N69: Chi | O69: South | P69: 2
A70: T100070 | B70: 27/10/2025 | C70: C3034 | E70: Male | F70: 130 | G70: Enugu | H70: Groceries | I70: Rice | J70: 456.44 | K70: 3 | L70: 0 | N70: Ada | O70: East | P70: 3
A71: T100071 | B71: 2025-07-19 | C71: C9830 | D71: James | E71: Female | F71: 42 | G71: Abuja | H71: Home | I71: Chair | J71: 159.08 | K71: -2 | L71: 120 | N71: Ben | O71: North
A72: T100072 | B72: 2025-01-20 | C72: C4142 | D72: Grace | E72: Male | F72: 130 | G72: PH | H72: Beauty | I72: Cream | J72: 328.53 | K72: -2 | L72: -10 | N72: Ada | O72: East | P72: 3
A73: T100073 | B73: 2025-09-29 | C73: C7135 | D73: John | E73: Male | F73: 130 | G73: PH | H73: Electronics | I73: Phone | J73: 223.95 | K73: -2 | L73: 0 | M73: Mobile Money | N73: Chi | O73: South | P73: 3
A74: T100074 | B74: 2025-03-20 | C74: C9233 | D74: Grace | E74: Female | F74: 130 | G74: Enugu | H74: Fashion | I74: Shirt | J74: 100.23 | K74: -2 | L74: 120 | M74: Transfer | N74: Ada | O74: South | P74: 1
A75: T100075 | B75: 2025-11-09 | C75: C7805 | D75: James | E75: Female | F75: 36 | G75: Enugu | H75: Home | I75: Chair | J75: 288.64 | K75: 1 | L75: 120 | M75: Mobile Money | N75: Ada | O75: East | P75: 5
A76: T100076 | B76: 2025-05-13 | C76: C2098 | D76: David | E76: Female | F76: 130 | G76: Abuja | H76: Electronics | I76: Phone | J76: 84.9 | K76: -2 | L76: 5 | M76: Mobile Money | N76: Chi | O76: West | P76: 3
A77: T100077 | B77: 29/12/2025 | C77: C2806 | D77: Peter | E77: Male | F77: 21 | G77: LAGOS | H77: Beauty | I77: Cream | J77: 105.76 | K77: 6 | L77: 5 | N77: Chi | O77: West | P77: 3
A78: T100078 | B78: 2025-04-06 | C78: C2788 | D78: David | E78: Female | F78: 44 | G78: LAGOS | H78: Beauty | I78: Cream | J78: 229.49 | K78: -2 | L78: -10 | M78: POS | N78: Ben | O78: South | P78: 3
A79: T100079 | B79: 2026-01-21 | C79: C6728 | D79: Peter | E79: Female | F79: 8 | G79: LAGOS | H79: Electronics | I79: Phone | J79: 297.94 | K79: -2 | L79: -10 | M79: Transfer | N79: Chi | O79: East
A80: T100080 | B80: 2025-04-23 | C80: C8672 | E80: Female | F80: 33 | G80: Kano | H80: Electronics | I80: Phone | J80: 256.49 | K80: 10 | L80: -10 | M80: Mobile Money | N80: Dan | O80: South | P80: 4
A81: T100081 | B81: 2025-08-19 | C81: C9970 | D81: Mary | E81: Female | F81: 130 | G81: Kano | H81: Beauty | I81: Cream | J81: 202.13 | K81: 2 | L81: -10 | M81: POS | N81: Dan | O81: South
A82: T100082 | B82: 2025-11-08 | C82: C4583 | D82: Grace | E82: Female | F82: 130 | G82: Abuja | H82: groceris | I82: Rice | J82: 376.61 | K82: 2 | L82: 15 | M82: Mobile Money | N82: Ben | O82: South | P82: 2
A83: T100083 | B83: 2026-05-30 | C83: C9000 | D83: Grace | E83: Male | F83: 36 | G83: LAGOS | H83: Sports | I83: Ball | J83: 50.76 | K83: -2 | L83: 120 | M83: Mobile Money | N83: Ben | O83: South | P83: 2
A84: T100084 | B84: 28/06/2025 | C84: C5862 | D84: David | E84: Female | F84: 23 | G84: Enugu | H84: Home | I84: Chair | J84: 164.1 | K84: 3 | L84: 10 | M84: POS | N84: Dan | O84: South | P84: 3
A85: T100085 | B85: 2026-04-05 | C85: C8114 | D85: John | E85: Female | F85: 8 | G85: Lagos | H85: Home | I85: Chair | J85: 15.36 | K85: 4 | L85: -10 | M85: POS | N85: Ben | O85: North | P85: 2
A86: T100086 | B86: 2025-06-03 | C86: C2837 | D86: David | E86: Male | F86: 63 | G86: Kano | H86: Sports | I86: Ball | J86: 418.34 | K86: 5 | L86: 5 | M86: Cash | N86: Ada | O86: South | P86: 1
A87: T100087 | B87: 2025-08-26 | C87: C8641 | D87: John | E87: Female | F87: 46 | G87: LAGOS | H87: Beauty | I87: Cream | J87: 214.36 | K87: -2 | L87: 15 | M87: POS | N87: Dan | O87: South
A88: T100088 | B88: 2026-05-18 | C88: C1455 | D88: Grace | E88: Male | F88: 8 | G88: LAGOS | H88: Beauty | I88: Cream | J88: 57.71 | K88: -2 | L88: -10 | M88: Cash | N88: Ben | O88: West | P88: 3
A89: T100089 | B89: 2025-11-17 | C89: C9562 | D89: Mary | E89: Male | F89: 8 | G89: Lagos | H89: Sports | I89: Ball | J89: 370.55 | K89: -2 | L89: 120 | M89: Transfer | N89: Ben | O89: West | P89: 4
A90: T100090 | B90: 2025-07-11 | C90: C5842 | D90: Peter | E90: Male | F90: 8 | G90: Kano | H90: Sports | I90: Ball | J90: 331.75 | K90: -2 | L90: 120 | N90: Ben | O90: East | P90: 2
A91: T100091 | B91: 08/06/2025 | C91: C5213 | D91: Peter | E91: Male | F91: 130 | G91: Abuja | H91: Fashion | I91: Shirt | J91: 265.26 | K91: -2 | L91: 0 | M91: POS | N91: Dan | O91: East | P91: 5
A92: T100092 | B92: 2025-05-30 | C92: C5086 | D92: Mary | E92: Male | F92: 59 | G92: lagos | H92: Electronics | I92: Phone | J92: 285.7 | K92: 4 | L92: 0 | N92: Ben | O92: West | P92: 5
A93: T100093 | B93: 2025-11-24 | C93: C7239 | D93: Grace | E93: Female | F93: 130 | G93: Lagos | H93: Groceries | I93: Rice | J93: 109.04 | K93: 3 | L93: 10 | M93: Mobile Money | N93: Ben | O93: North | P93: 3
A94: T100094 | B94: 2025-06-11 | C94: C1489 | D94: Peter | E94: Male | F94: 130 | G94: LAGOS | H94: Beauty | I94: Cream | J94: 322.57 | K94: 8 | L94: 10 | M94: Cash | N94: Dan | O94: West | P94: 5
A95: T100095 | B95: 2025-05-30 | C95: C4488 | D95: David | E95: Male | F95: 130 | G95: Abuja | H95: Sports | I95: Ball | J95: 350.62 | K95: -2 | L95: 15 | N95: Ben | O95: East | P95: 2
A96: T100096 | B96: 2026-01-21 | C96: C9757 | D96: John | E96: Male | F96: 43 | G96: Kano | H96: Groceries | I96: Rice | J96: 499.74 | K96: 1 | L96: 10 | N96: Dan | O96: East | P96: 1
A97: T100097 | B97: 2025-03-19 | C97: C9462 | D97: David | E97: Female | F97: 29 | G97: lagos | H97: Home | I97: Chair | J97: 304.02 | K97: 6 | L97: 120 | M97: Mobile Money | N97: Dan | O97: South | P97: 2
A98: T100098 | B98: 17/07/2025 | C98: C4611 | D98: David | E98: Female | F98: 25 | G98: PH | H98: Home | I98: Chair | J98: 137.31 | K98: 3 | L98: 10 | M98: Cash | N98: Ben | O98: West | P98: 5
A99: T100099 | B99: 2025-12-03 | C99: C6147 | D99: Grace | E99: Female | F99: 8 | G99: lagos | H99: groceris | I99: Rice | J99: 353.95 | K99: -2 | L99: 15 | M99: Cash | N99: Ben | O99: North | P99: 5
A100: T100100 | B100: 2026-04-21 | C100: C7371 | D100: Grace | E100: Male | F100: 34 | G100: LAGOS | H100: groceris | I100: Rice | J100: 218.73 | K100: 10 | L100: 0 | M100: POS | N100: Ada | O100: East | P100: 5
A101: T100101 | B101: 2025-08-23 | C101: C7489 | D101: James | E101: Male | F101: 130 | G101: Enugu | H101: Groceries | I101: Rice | J101: 225.05 | K101: -2 | L101: 120 | M101: Mobile Money | N101: Ada | O101: East | P101: 2
A102: T100102 | B102: 2025-11-28 | C102: C9515 | D102: Peter | E102: Male | F102: 130 | G102: LAGOS | H102: Groceries | I102: Rice | J102: 256.71 | K102: 6 | L102: 0 | M102: POS | N102: Ben | O102: East | P102: 4
A103: T100103 | B103: 2025-05-26 | C103: C3710 | D103: Peter | E103: Female | F103: 130 | G103: Enugu | H103: Groceries | I103: Rice | J103: 245.32 | K103: 4 | L103: 15 | M103: POS | N103: Ada | O103: East
...

Sheet Pivot Tables
B3: Row Labels | C3: Sum of Total_sales
B4: Electronics | C4: 58846.282
B5: Fashion | C5: 40216.066
B6: Grand Total | C6: 99062.348
B15: Row Labels | C15: Sum of Total_sales
B16: Ada | C16: 232281.62
B17: Ben | C17: 172623.49
B18: Chi | C18: 171840.88
B19: Dan | C19: 189322.94
B20: (blank)
B21: Grand Total | C21: 766068.92
B25: Row Labels | C25: Sum of Total_sales
B26: East | C26: 192925.66
B27: North | C27: 209640.86
B28: South | C28: 168416.76
B29: West | C29: 195085.64
B30: (blank)
B31: Grand Total | C31: 766068.92
B36: Row Labels | C36: Sum of Total_sales
B37: Abuja | C37: 138012.53
B38: Enugu | C38: 107638.82
B39: Kano | C39: 107389.43
B40: Lagos | C40: 308160.4
B41: Ph | C41: 104867.74
B42: (blank)
B43: Grand Total | C43: 766068.92
B48: Row Labels | C48: Sum of Total_sales
C49: 165592.05
B50: Cash | C50: 163846.56
B51: Mobile Money | C51: 139579.29
B52: Pos | C52: 142010.37
B53: Transfer | C53: 155040.65
B54: Grand Total | C54: 766068.92

Sheet WORKING DATA
A1: Transaction_ID | B1: Date | C1: Customer_ID | D1: Customer_Name | E1: Clean_Customers_Name | F1: Gender | G1: Age | H1: Clean_Age | I1: City | J1: Clean_City | K1: Product_Category | L1: Clean_Product_Name | M1: Product_Name | N1: Clean_Unit_Price | O1: Unit_Price | P1: Quantity | Q1: Clean_Quantity | R1: Discount (%) | S1: Clean_Discount | T1: Payment_Method | U1: Clean_payment_Method | V1: Salesperson | W1: Clean_salesperson | X1: Branch | Y1: Customer_Rating | Z1: Missing Data check | AA1: Total_sales
A2: T100002 | B2: 2025-10-06 | C2: C9114 | D2: Peter | E2: =PROPER(TRIM(D2)) -> Peter | F2: Male | G2: 130 | H2: =IF(AND(G2>18, G2<65), "Valid", "Invalid") -> Invalid | I2: lagos | J2: =PROPER(TRIM(I2)) -> Lagos | K2: Fashion | L2: =PROPER(TRIM(K2)) -> Fashion | M2: Shirt | N2: =PROPER(TRIM(M2)) -> Shirt | O2: 237.91 | P2: -2 | Q2: =IF(P2<1, 1, P2) -> 1 | R2: -10 | S2: =IF(OR(R2<0,R2>100),"invalid","Valid") -> invalid | T2: POS | U2: =PROPER(TRIM(T2)) -> Pos | V2: Dan | W2: =PROPER(TRIM(V2)) -> Dan | X2: North | Y2: 4 | Z2: =IF(D2="", "Missing", "ok") -> ok | AA2: =(O2*Q2)*(1-R2/100) -> 261.701
A3: T100003 | B3: 2025-02-22 | C3: C7218 | D3: Peter | E3: =PROPER(TRIM(D3)) -> Peter | F3: Male | G3: 22 | H3: =IF(AND(G3>18, G3<65), "Valid", "Invalid") -> Valid | I3: LAGOS | J3: =PROPER(TRIM(I3)) -> Lagos | K3: Sports | L3: =PROPER(TRIM(K3)) -> Sports | M3: Ball | N3: =PROPER(TRIM(M3)) -> Ball | O3: 103.48 | P3: -2 | Q3: =IF(P3<1, 1, P3) -> 1 | R3: 0 | S3: =IF(OR(R3<0,R3>100),"invalid","Valid") -> Valid | U3: =PROPER(TRIM(T3)) | V3: Dan | W3: =PROPER(TRIM(V3)) -> Dan | X3: West | Y3: 4 | Z3: =IF(D3="", "Missing", "ok") -> ok | AA3: =(O3*Q3)*(1-R3/100) -> 103.48
A4: T100004 | B4: 2026-04-20 | C4: C9957 | D4: Aisha | E4: =PROPER(TRIM(D4)) -> Aisha | F4: Male | G4: 55 | H4: =IF(AND(G4>18, G4<65), "Valid", "Invalid") -> Valid | I4: PH | J4: =PROPER(TRIM(I4)) -> Ph | K4: Electronics | L4: =PROPER(TRIM(K4)) -> Electronics | M4: Phone | N4: =PROPER(TRIM(M4)) -> Phone | O4: 436.14 | P4: -2 | Q4: =IF(P4<1, 1, P4) -> 1 | R4: 10 | S4: =IF(OR(R4<0,R4>100),"invalid","Valid") -> Valid | T4: POS | U4: =PROPER(TRIM(T4)) -> Pos | V4: Chi | W4: =PROPER(TRIM(V4)) -> Chi | X4: West | Z4: =IF(D4="", "Missing", "ok") -> ok | AA4: =(O4*Q4)*(1-R4/100) -> 392.526
A5: T100005 | B5: 2026-02-21 | C5: C1077 | D5: James | E5: =PROPER(TRIM(D5)) -> James | F5: Female | G5: 130 | H5: =IF(AND(G5>18, G5<65), "Valid", "Invalid") -> Invalid | I5: Enugu | J5: =PROPER(TRIM(I5)) -> Enugu | K5: Groceries | L5: =PROPER(TRIM(K5)) -> Groceries | M5: Rice | N5: =PROPER(TRIM(M5)) -> Rice | O5: 430.25 | P5: -2 | Q5: =IF(P5<1, 1, P5) -> 1 | R5: 10 | S5: =IF(OR(R5<0,R5>100),"invalid","Valid") -> Valid | U5: =PROPER(TRIM(T5)) | V5: Chi | W5: =PROPER(TRIM(V5)) -> Chi | X5: West | Y5: 2 | Z5: =IF(D5="", "Missing", "ok") -> ok | AA5: =(O5*Q5)*(1-R5/100) -> 387.225
A6: T100006 | B6: 2025-10-13 | C6: C6441 | E6: =PROPER(TRIM(D6)) | F6: Female | G6: 37 | H6: =IF(AND(G6>18, G6<65), "Valid", "Invalid") -> Valid | I6: Lagos | J6: =PROPER(TRIM(I6)) -> Lagos | K6: Home | L6: =PROPER(TRIM(K6)) -> Home | M6: Chair | N6: =PROPER(TRIM(M6)) -> Chair | O6: 44.01 | P6: -2 | Q6: =IF(P6<1, 1, P6) -> 1 | R6: 120 | S6: =IF(OR(R6<0,R6>100),"invalid","Valid") -> invalid | T6: POS | U6: =PROPER(TRIM(T6)) -> Pos | V6: Dan | W6: =PROPER(TRIM(V6)) -> Dan | X6: West | Y6: 4 | Z6: =IF(D6="", "Missing", "ok") -> Missing | AA6: =(O6*Q6)*(1-R6/100) -> -8.802
A7: T100007 | B7: 10/11/2025 | C7: C6943 | D7: Aisha | E7: =PROPER(TRIM(D7)) -> Aisha | F7: Female | G7: 130 | H7: =IF(AND(G7>18, G7<65), "Valid", "Invalid") -> Invalid | I7: Lagos | J7: =PROPER(TRIM(I7)) -> Lagos | K7: Sports | L7: =PROPER(TRIM(K7)) -> Sports | M7: Ball | N7: =PROPER(TRIM(M7)) -> Ball | O7: 356.22 | P7: -2 | Q7: =IF(P7<1, 1, P7) -> 1 | R7: 5 | S7: =IF(OR(R7<0,R7>100),"invalid","Valid") -> Valid | T7: Mobile Money | U7: =PROPER(TRIM(T7)) -> Mobile Money | V7: Chi | W7: =PROPER(TRIM(V7)) -> Chi | X7: West | Y7: 1 | Z7: =IF(D7="", "Missing", "ok") -> ok | AA7: =(O7*Q7)*(1-R7/100) -> 338.409
A8: T100008 | B8: 2025-08-17 | C8: C1101 | D8: John | E8: =PROPER(TRIM(D8)) -> John | F8: Female | G8: 8 | H8: =IF(AND(G8>18, G8<65), "Valid", "Invalid") -> Invalid | I8: Enugu | J8: =PROPER(TRIM(I8)) -> Enugu | K8: Electronics | L8: =PROPER(TRIM(K8)) -> Electronics | M8: Phone | N8: =PROPER(TRIM(M8)) -> Phone | O8: 323.16 | P8: 4 | Q8: =IF(P8<1, 1, P8) -> 4 | R8: 120 | S8: =IF(OR(R8<0,R8>100),"invalid","Valid") -> invalid | T8: Transfer | U8: =PROPER(TRIM(T8)) -> Transfer | V8: Chi | W8: =PROPER(TRIM(V8)) -> Chi | X8: South | Z8: =IF(D8="", "Missing", "ok") -> ok | AA8: =(O8*Q8)*(1-R8/100) -> -258.528
A9: T100009 | B9: 2025-04-07 | C9: C8179 | D9: Mary | E9: =PROPER(TRIM(D9)) -> Mary | F9: Female | G9: 30 | H9: =IF(AND(G9>18, G9<65), "Valid", "Invalid") -> Valid | I9: Abuja | J9: =PROPER(TRIM(I9)) -> Abuja | K9: Sports | L9: =PROPER(TRIM(K9)) -> Sports | M9: Ball | N9: =PROPER(TRIM(M9)) -> Ball | O9: 126.25 | P9: 7 | Q9: =IF(P9<1, 1, P9) -> 7 | R9: 0 | S9: =IF(OR(R9<0,R9>100),"invalid","Valid") -> Valid | U9: =PROPER(TRIM(T9)) | V9: Dan | W9: =PROPER(TRIM(V9)) -> Dan | X9: West | Y9: 4 | Z9: =IF(D9="", "Missing", "ok") -> ok | AA9: =(O9*Q9)*(1-R9/100) -> 883.75
A10: T100010 | B10: 2025-04-01 | C10: C2862 | D10: Aisha | E10: =PROPER(TRIM(D10)) -> Aisha | F10: Male | G10: 8 | H10: =IF(AND(G10>18, G10<65), "Valid", "Invalid") -> Invalid | I10: Abuja | J10: =PROPER(TRIM(I10)) -> Abuja | K10: Sports | L10: =PROPER(TRIM(K10)) -> Sports | M10: Ball | N10: =PROPER(TRIM(M10)) -> Ball | O10: 233.45 | P10: 8 | Q10: =IF(P10<1, 1, P10) -> 8 | R10: 10 | S10: =IF(OR(R10<0,R10>100),"invalid","Valid") -> Valid | U10: =PROPER(TRIM(T10)) | V10: Chi | W10: =PROPER(TRIM(V10)) -> Chi | X10: North | Y10: 1 | Z10: =IF(D10="", "Missing", "ok") -> ok | AA10: =(O10*Q10)*(1-R10/100) -> 1680.84
A11: T100011 | B11: 2025-09-10 | C11: C4724 | D11: Peter | E11: =PROPER(TRIM(D11)) -> Peter | F11: Female | G11: 8 | H11: =IF(AND(G11>18, G11<65), "Valid", "Invalid") -> Invalid | I11: PH | J11: =PROPER(TRIM(I11)) -> Ph | K11: Electronics | L11: =PROPER(TRIM(K11)) -> Electronics | M11: Phone | N11: =PROPER(TRIM(M11)) -> Phone | O11: 150.57 | P11: -2 | Q11: =IF(P11<1, 1, P11) -> 1 | R11: 10 | S11: =IF(OR(R11<0,R11>100),"invalid","Valid") -> Valid | T11: Cash | U11: =PROPER(TRIM(T11)) -> Cash | V11: Chi | W11: =PROPER(TRIM(V11)) -> Chi | X11: West | Y11: 4 | Z11: =IF(D11="", "Missing", "ok") -> ok | AA11: =(O11*Q11)*(1-R11/100) -> 135.513
A12: T100012 | B12: 2025-02-07 | C12: C2129 | D12: James | E12: =PROPER(TRIM(D12)) -> James | F12: Female | G12: 8 | H12: =IF(AND(G12>18, G12<65), "Valid", "Invalid") -> Invalid | I12: Lagos | J12: =PROPER(TRIM(I12)) -> Lagos | K12: Fashion | L12: =PROPER(TRIM(K12)) -> Fashion | M12: Shirt | N12: =PROPER(TRIM(M12)) -> Shirt | O12: 49.62 | P12: 7 | Q12: =IF(P12<1, 1, P12) -> 7 | R12: 120 | S12: =IF(OR(R12<0,R12>100),"invalid","Valid") -> invalid | T12: Mobile Money | U12: =PROPER(TRIM(T12)) -> Mobile Money | V12: Ada | W12: =PROPER(TRIM(V12)) -> Ada | X12: East | Y12: 4 | Z12: =IF(D12="", "Missing", "ok") -> ok | AA12: =(O12*Q12)*(1-R12/100) -> -69.468
A13: T100013 | B13: 2025-06-09 | C13: C4291 | D13: Peter | E13: =PROPER(TRIM(D13)) -> Peter | F13: Male | G13: 130 | H13: =IF(AND(G13>18, G13<65), "Valid", "Invalid") -> Invalid | I13: Kano | J13: =PROPER(TRIM(I13)) -> Kano | K13: groceris | L13: =PROPER(TRIM(K13)) -> Groceris | M13: Rice | N13: =PROPER(TRIM(M13)) -> Rice | O13: 409.19 | P13: -2 | Q13: =IF(P13<1, 1, P13) -> 1 | R13: 120 | S13: =IF(OR(R13<0,R13>100),"invalid","Valid") -> invalid | T13: POS | U13: =PROPER(TRIM(T13)) -> Pos | V13: Ada | W13: =PROPER(TRIM(V13)) -> Ada | X13: West | Y13: 5 | Z13: =IF(D13="", "Missing", "ok") -> ok | AA13: =(O13*Q13)*(1-R13/100) -> -81.838
A14: T100014 | B14: 12/04/2025 | C14: C1596 | D14: John | E14: =PROPER(TRIM(D14)) -> John | F14: Male | G14: 130 | H14: =IF(AND(G14>18, G14<65), "Valid", "Invalid") -> Invalid | I14: Kano | J14: =PROPER(TRIM(I14)) -> Kano | K14: Home | L14: =PROPER(TRIM(K14)) -> Home | M14: Chair | N14: =PROPER(TRIM(M14)) -> Chair | O14: 126.04 | P14: -2 | Q14: =IF(P14<1, 1, P14) -> 1 | R14: 15 | S14: =IF(OR(R14<0,R14>100),"invalid","Valid") -> Valid | T14: Transfer | U14: =PROPER(TRIM(T14)) -> Transfer | V14: Ben | W14: =PROPER(TRIM(V14)) -> Ben | X14: South | Y14: 4 | Z14: =IF(D14="", "Missing", "ok") -> ok | AA14: =(O14*Q14)*(1-R14/100) -> 107.134
A15: T100015 | B15: 2025-10-21 | C15: C1752 | D15: Aisha | E15: =PROPER(TRIM(D15)) -> Aisha | F15: Female | G15: 130 | H15: =IF(AND(G15>18, G15<65), "Valid", "Invalid") -> Invalid | I15: Lagos | J15: =PROPER(TRIM(I15)) -> Lagos | K15: Groceries | L15: =PROPER(TRIM(K15)) -> Groceries | M15: Rice | N15: =PROPER(TRIM(M15)) -> Rice | O15: 477.09 | P15: -2 | Q15: =IF(P15<1, 1, P15) -> 1 | R15: 0 | S15: =IF(OR(R15<0,R15>100),"invalid","Valid") -> Valid | T15: Mobile Money | U15: =PROPER(TRIM(T15)) -> Mobile Money | V15: Dan | W15: =PROPER(TRIM(V15)) -> Dan | X15: East | Y15: 4 | Z15: =IF(D15="", "Missing", "ok") -> ok | AA15: =(O15*Q15)*(1-R15/100) -> 477.09
A16: T100016 | B16: 2025-05-25 | C16: C5577 | D16: Mary | E16: =PROPER(TRIM(D16)) -> Mary | F16: Male | G16: 130 | H16: =IF(AND(G16>18, G16<65), "Valid", "Invalid") -> Invalid | I16: Lagos | J16: =PROPER(TRIM(I16)) -> Lagos | K16: groceris | L16: =PROPER(TRIM(K16)) -> Groceris | M16: Rice | N16: =PROPER(TRIM(M16)) -> Rice | O16: 332 | P16: -2 | Q16: =IF(P16<1, 1, P16) -> 1 | R16: 5 | S16: =IF(OR(R16<0,R16>100),"invalid","Valid") -> Valid | T16: Transfer | U16: =PROPER(TRIM(T16)) -> Transfer | V16: Dan | W16: =PROPER(TRIM(V16)) -> Dan | X16: East | Y16: 4 | Z16: =IF(D16="", "Missing", "ok") -> ok | AA16: =(O16*Q16)*(1-R16/100) -> 315.4
A17: T100017 | B17: 2025-01-24 | C17: C8070 | D17: Grace | E17: =PROPER(TRIM(D17)) -> Grace | F17: Male | G17: 28 | H17: =IF(AND(G17>18, G17<65), "Valid", "Invalid") -> Valid | I17: Lagos | J17: =PROPER(TRIM(I17)) -> Lagos | K17: groceris | L17: =PROPER(TRIM(K17)) -> Groceris | M17: Rice | N17: =PROPER(TRIM(M17)) -> Rice | O17: 484.12 | P17: 1 | Q17: =IF(P17<1, 1, P17) -> 1 | R17: -10 | S17: =IF(OR(R17<0,R17>100),"invalid","Valid") -> invalid | T17: POS | U17: =PROPER(TRIM(T17)) -> Pos | V17: Dan | W17: =PROPER(TRIM(V17)) -> Dan | X17: North | Y17: 2 | Z17: =IF(D17="", "Missing", "ok") -> ok | AA17: =(O17*Q17)*(1-R17/100) -> 532.532
A18: T100018 | B18: 2026-02-22 | C18: C3714 | E18: =PROPER(TRIM(D18)) | F18: Female | G18: 8 | H18: =IF(AND(G18>18, G18<65), "Valid", "Invalid") -> Invalid | I18: Kano | J18: =PROPER(TRIM(I18)) -> Kano | K18: groceris | L18: =PROPER(TRIM(K18)) -> Groceris | M18: Rice | N18: =PROPER(TRIM(M18)) -> Rice | O18: 487.9 | P18: 6 | Q18: =IF(P18<1, 1, P18) -> 6 | R18: -10 | S18: =IF(OR(R18<0,R18>100),"invalid","Valid") -> invalid | T18: Transfer | U18: =PROPER(TRIM(T18)) -> Transfer | V18: Ada | W18: =PROPER(TRIM(V18)) -> Ada | X18: South | Y18: 2 | Z18: =IF(D18="", "Missing", "ok") -> Missing | AA18: =(O18*Q18)*(1-R18/100) -> 3220.14
A19: T100019 | B19: 2025-07-11 | C19: C4372 | D19: Peter | E19: =PROPER(TRIM(D19)) -> Peter | F19: Female | G19: 43 | H19: =IF(AND(G19>18, G19<65), "Valid", "Invalid") -> Valid | I19: Abuja | J19: =PROPER(TRIM(I19)) -> Abuja | K19: Sports | L19: =PROPER(TRIM(K19)) -> Sports | M19: Ball | N19: =PROPER(TRIM(M19)) -> Ball | O19: 398.62 | P19: -2 | Q19: =IF(P19<1, 1, P19) -> 1 | R19: 10 | S19: =IF(OR(R19<0,R19>100),"invalid","Valid") -> Valid | U19: =PROPER(TRIM(T19)) | V19: Ben | W19: =PROPER(TRIM(V19)) -> Ben | X19: West | Y19: 1 | Z19: =IF(D19="", "Missing", "ok") -> ok | AA19: =(O19*Q19)*(1-R19/100) -> 358.758
A20: T100020 | B20: 2026-02-25 | C20: C1826 | D20: Mary | E20: =PROPER(TRIM(D20)) -> Mary | F20: Male | G20: 130 | H20: =IF(AND(G20>18, G20<65), "Valid", "Invalid") -> Invalid | I20: Kano | J20: =PROPER(TRIM(I20)) -> Kano | K20: groceris | L20: =PROPER(TRIM(K20)) -> Groceris | M20: Rice | N20: =PROPER(TRIM(M20)) -> Rice | O20: 68.67 | P20: 4 | Q20: =IF(P20<1, 1, P20) -> 4 | R20: 10 | S20: =IF(OR(R20<0,R20>100),"invalid","Valid") -> Valid | U20: =PROPER(TRIM(T20)) | V20: Ben | W20: =PROPER(TRIM(V20)) -> Ben | X20: West | Z20: =IF(D20="", "Missing", "ok") -> ok | AA20: =(O20*Q20)*(1-R20/100) -> 247.212
A21: T100021 | B21: 02/07/2025 | C21: C8532 | D21: John | E21: =PROPER(TRIM(D21)) -> John | F21: Male | G21: 8 | H21: =IF(AND(G21>18, G21<65), "Valid", "Invalid") -> Invalid | I21: Abuja | J21: =PROPER(TRIM(I21)) -> Abuja | K21: Fashion | L21: =PROPER(TRIM(K21)) -> Fashion | M21: Shirt | N21: =PROPER(TRIM(M21)) -> Shirt | O21: 477.46 | P21: -2 | Q21: =IF(P21<1, 1, P21) -> 1 | R21: -10 | S21: =IF(OR(R21<0,R21>100),"invalid","Valid") -> invalid | T21: Cash | U21: =PROPER(TRIM(T21)) -> Cash | V21: Ada | W21: =PROPER(TRIM(V21)) -> Ada | X21: West | Y21: 2 | Z21: =IF(D21="", "Missing", "ok") -> ok | AA21: =(O21*Q21)*(1-R21/100) -> 525.206
A22: T100022 | B22: 2025-10-19 | C22: C1462 | D22: David | E22: =PROPER(TRIM(D22)) -> David | F22: Male | G22: 130 | H22: =IF(AND(G22>18, G22<65), "Valid", "Invalid") -> Invalid | I22: Enugu | J22: =PROPER(TRIM(I22)) -> Enugu | K22: Sports | L22: =PROPER(TRIM(K22)) -> Sports | M22: Ball | N22: =PROPER(TRIM(M22)) -> Ball | O22: 29.5 | P22: -2 | Q22: =IF(P22<1, 1, P22) -> 1 | R22: 120 | S22: =IF(OR(R22<0,R22>100),"invalid","Valid") -> invalid | T22: Cash | U22: =PROPER(TRIM(T22)) -> Cash | V22: Dan | W22: =PROPER(TRIM(V22)) -> Dan | X22: South | Y22: 3 | Z22: =IF(D22="", "Missing", "ok") -> ok | AA22: =(O22*Q22)*(1-R22/100) -> -5.9
A23: T100023 | B23: 2025-08-16 | C23: C6481 | D23: James | E23: =PROPER(TRIM(D23)) -> James | F23: Male | G23: 8 | H23: =IF(AND(G23>18, G23<65), "Valid", "Invalid") -> Invalid | I23: lagos | J23: =PROPER(TRIM(I23)) -> Lagos | K23: Beauty | L23: =PROPER(TRIM(K23)) -> Beauty | M23: Cream | N23: =PROPER(TRIM(M23)) -> Cream | O23: 134.08 | P23: 5 | Q23: =IF(P23<1, 1, P23) -> 5 | R23: 0 | S23: =IF(OR(R23<0,R23>100),"invalid","Valid") -> Valid | U23: =PROPER(TRIM(T23)) | V23: Ben | W23: =PROPER(TRIM(V23)) -> Ben | X23: South | Y23: 2 | Z23: =IF(D23="", "Missing", "ok") -> ok | AA23: =(O23*Q23)*(1-R23/100) -> 670.4
A24: T100024 | B24: 2025-09-24 | C24: C2962 | D24: Grace | E24: =PROPER(TRIM(D24)) -> Grace | F24: Female | G24: 130 | H24: =IF(AND(G24>18, G24<65), "Valid", "Invalid") -> Invalid | I24: Abuja | J24: =PROPER(TRIM(I24)) -> Abuja | K24: Fashion | L24: =PROPER(TRIM(K24)) -> Fashion | M24: Shirt | N24: =PROPER(TRIM(M24)) -> Shirt | O24: 388.4 | P24: -2 | Q24: =IF(P24<1, 1, P24) -> 1 | R24: 15 | S24: =IF(OR(R24<0,R24>100),"invalid","Valid") -> Valid | T24: Mobile Money | U24: =PROPER(TRIM(T24)) -> Mobile Money | V24: Ada | W24: =PROPER(TRIM(V24)) -> Ada | X24: North | Y24: 1 | Z24: =IF(D24="", "Missing", "ok") -> ok | AA24: =(O24*Q24)*(1-R24/100) -> 330.14
A25: T100025 | B25: 2025-06-10 | C25: C3575 | D25: James | E25: =PROPER(TRIM(D25)) -> James | F25: Female | G25: 130 | H25: =IF(AND(G25>18, G25<65), "Valid", "Invalid") -> Invalid | I25: Kano | J25: =PROPER(TRIM(I25)) -> Kano | K25: Fashion | L25: =PROPER(TRIM(K25)) -> Fashion | M25: Shirt | N25: =PROPER(TRIM(M25)) -> Shirt | O25: 279.11 | P25: -2 | Q25: =IF(P25<1, 1, P25) -> 1 | R25: 10 | S25: =IF(OR(R25<0,R25>100),"invalid","Valid") -> Valid | T25: Transfer | U25: =PROPER(TRIM(T25)) -> Transfer | V25: Ben | W25: =PROPER(TRIM(V25)) -> Ben | X25: West | Z25: =IF(D25="", "Missing", "ok") -> ok | AA25: =(O25*Q25)*(1-R25/100) -> 251.199
A26: T100026 | B26: 2025-05-26 | C26: C5211 | D26: David | E26: =PROPER(TRIM(D26)) -> David | F26: Male | G26: 130 | H26: =IF(AND(G26>18, G26<65), "Valid", "Invalid") -> Invalid | I26: Abuja | J26: =PROPER(TRIM(I26)) -> Abuja | K26: Beauty | L26: =PROPER(TRIM(K26)) -> Beauty | M26: Cream | N26: =PROPER(TRIM(M26)) -> Cream | O26: 205.37 | P26: -2 | Q26: =IF(P26<1, 1, P26) -> 1 | R26: -10 | S26: =IF(OR(R26<0,R26>100),"invalid","Valid") -> invalid | T26: Cash | U26: =PROPER(TRIM(T26)) -> Cash | V26: Ada | W26: =PROPER(TRIM(V26)) -> Ada | X26: North | Z26: =IF(D26="", "Missing", "ok") -> ok | AA26: =(O26*Q26)*(1-R26/100) -> 225.907
A27: T100027 | B27: 2025-05-27 | C27: C5215 | D27: Aisha | E27: =PROPER(TRIM(D27)) -> Aisha | F27: Female | G27: 58 | H27: =IF(AND(G27>18, G27<65), "Valid", "Invalid") -> Valid | I27: PH | J27: =PROPER(TRIM(I27)) -> Ph | K27: groceris | L27: =PROPER(TRIM(K27)) -> Groceris | M27: Rice | N27: =PROPER(TRIM(M27)) -> Rice | O27: 72.55 | P27: 6 | Q27: =IF(P27<1, 1, P27) -> 6 | R27: 15 | S27: =IF(OR(R27<0,R27>100),"invalid","Valid") -> Valid | T27: Mobile Money | U27: =PROPER(TRIM(T27)) -> Mobile Money | V27: Ben | W27: =PROPER(TRIM(V27)) -> Ben | X27: East | Y27: 1 | Z27: =IF(D27="", "Missing", "ok") -> ok | AA27: =(O27*Q27)*(1-R27/100) -> 370.005
A28: T100028 | B28: 07/01/2025 | C28: C8821 | D28: Mary | E28: =PROPER(TRIM(D28)) -> Mary | F28: Female | G28: 130 | H28: =IF(AND(G28>18, G28<65), "Valid", "Invalid") -> Invalid | I28: lagos | J28: =PROPER(TRIM(I28)) -> Lagos | K28: groceris | L28: =PROPER(TRIM(K28)) -> Groceris | M28: Rice | N28: =PROPER(TRIM(M28)) -> Rice | O28: 275.95 | P28: -2 | Q28: =IF(P28<1, 1, P28) -> 1 | R28: 10 | S28: =IF(OR(R28<0,R28>100),"invalid","Valid") -> Valid | U28: =PROPER(TRIM(T28)) | V28: Dan | W28: =PROPER(TRIM(V28)) -> Dan | X28: West | Y28: 3 | Z28: =IF(D28="", "Missing", "ok") -> ok | AA28: =(O28*Q28)*(1-R28/100) -> 248.355
A29: T100029 | B29: 2025-10-19 | C29: C2182 | D29: Aisha | E29: =PROPER(TRIM(D29)) -> Aisha | F29: Female | G29: 8 | H29: =IF(AND(G29>18, G29<65), "Valid", "Invalid") -> Invalid | I29: Enugu | J29: =PROPER(TRIM(I29)) -> Enugu | K29: Beauty | L29: =PROPER(TRIM(K29)) -> Beauty | M29: Cream | N29: =PROPER(TRIM(M29)) -> Cream | O29: 161.33 | P29: 4 | Q29: =IF(P29<1, 1, P29) -> 4 | R29: 10 | S29: =IF(OR(R29<0,R29>100),"invalid","Valid") -> Valid | T29: Cash | U29: =PROPER(TRIM(T29)) -> Cash | V29: Ben | W29: =PROPER(TRIM(V29)) -> Ben | X29: East | Y29: 3 | Z29: =IF(D29="", "Missing", "ok") -> ok | AA29: =(O29*Q29)*(1-R29/100) -> 580.788
A30: T100030 | B30: 2026-01-06 | C30: C5052 | E30: =PROPER(TRIM(D30)) | F30: Female | G30: 58 | H30: =IF(AND(G30>18, G30<65), "Valid", "Invalid") -> Valid | I30: Lagos | J30: =PROPER(TRIM(I30)) -> Lagos | K30: Beauty | L30: =PROPER(TRIM(K30)) -> Beauty | M30: Cream | N30: =PROPER(TRIM(M30)) -> Cream | O30: 416.14 | P30: 10 | Q30: =IF(P30<1, 1, P30) -> 10 | R30: 120 | S30: =IF(OR(R30<0,R30>100),"invalid","Valid") -> invalid | T30: Mobile Money | U30: =PROPER(TRIM(T30)) -> Mobile Money | V30: Ada | W30: =PROPER(TRIM(V30)) -> Ada | X30: North | Y30: 1 | Z30: =IF(D30="", "Missing", "ok") -> Missing | AA30: =(O30*Q30)*(1-R30/100) -> -832.28
A31: T100031 | B31: 2026-02-16 | C31: C6457 | D31: John | E31: =PROPER(TRIM(D31)) -> John | F31: Male | G31: 8 | H31: =IF(AND(G31>18, G31<65), "Valid", "Invalid") -> Invalid | I31: PH | J31: =PROPER(TRIM(I31)) -> Ph | K31: groceris | L31: =PROPER(TRIM(K31)) -> Groceris | M31: Rice | N31: =PROPER(TRIM(M31)) -> Rice | O31: 258.57 | P31: 2 | Q31: =IF(P31<1, 1, P31) -> 2 | R31: -10 | S31: =IF(OR(R31<0,R31>100),"invalid","Valid") -> invalid | T31: POS | U31: =PROPER(TRIM(T31)) -> Pos | V31: Ben | W31: =PROPER(TRIM(V31)) -> Ben | X31: West | Y31: 3 | Z31: =IF(D31="", "Missing", "ok") -> ok | AA31: =(O31*Q31)*(1-R31/100) -> 568.854
A32: T100032 | B32: 2025-03-23 | C32: C8802 | D32: John | E32: =PROPER(TRIM(D32)) -> John | F32: Male | G32: 130 | H32: =IF(AND(G32>18, G32<65), "Valid", "Invalid") -> Invalid | I32: LAGOS | J32: =PROPER(TRIM(I32)) -> Lagos | K32: Sports | L32: =PROPER(TRIM(K32)) -> Sports | M32: Ball | N32: =PROPER(TRIM(M32)) -> Ball | O32: 395.37 | P32: -2 | Q32: =IF(P32<1, 1, P32) -> 1 | R32: 5 | S32: =IF(OR(R32<0,R32>100),"invalid","Valid") -> Valid | T32: Mobile Money | U32: =PROPER(TRIM(T32)) -> Mobile Money | V32: Ada | W32: =PROPER(TRIM(V32)) -> Ada | X32: South | Y32: 4 | Z32: =IF(D32="", "Missing", "ok") -> ok | AA32: =(O32*Q32)*(1-R32/100) -> 375.6015
A33: T100033 | B33: 2025-10-09 | C33: C7652 | D33: Aisha | E33: =PROPER(TRIM(D33)) -> Aisha | F33: Male | G33: 37 | H33: =IF(AND(G33>18, G33<65), "Valid", "Invalid") -> Valid | I33: Kano | J33: =PROPER(TRIM(I33)) -> Kano | K33: Sports | L33: =PROPER(TRIM(K33)) -> Sports | M33: Ball | N33: =PROPER(TRIM(M33)) -> Ball | O33: 429.08 | P33: 9 | Q33: =IF(P33<1, 1, P33) -> 9 | R33: 0 | S33: =IF(OR(R33<0,R33>100),"invalid","Valid") -> Valid | T33: Mobile Money | U33: =PROPER(TRIM(T33)) -> Mobile Money | V33: Chi | W33: =PROPER(TRIM(V33)) -> Chi | X33: East | Y33: 4 | Z33: =IF(D33="", "Missing", "ok") -> ok | AA33: =(O33*Q33)*(1-R33/100) -> 3861.72
A34: T100034 | B34: 2025-07-11 | C34: C9293 | D34: David | E34: =PROPER(TRIM(D34)) -> David | F34: Female | G34: 35 | H34: =IF(AND(G34>18, G34<65), "Valid", "Invalid") -> Valid | I34: Enugu | J34: =PROPER(TRIM(I34)) -> Enugu | K34: groceris | L34: =PROPER(TRIM(K34)) -> Groceris | M34: Rice | N34: =PROPER(TRIM(M34)) -> Rice | O34: 467.61 | P34: -2 | Q34: =IF(P34<1, 1, P34) -> 1 | R34: 120 | S34: =IF(OR(R34<0,R34>100),"invalid","Valid") -> invalid | T34: Transfer | U34: =PROPER(TRIM(T34)) -> Transfer | V34: Chi | W34: =PROPER(TRIM(V34)) -> Chi | X34: East | Y34: 4 | Z34: =IF(D34="", "Missing", "ok") -> ok | AA34: =(O34*Q34)*(1-R34/100) -> -93.522
A35: T100035 | B35: 13/03/2026 | C35: C2683 | D35: Mary | E35: =PROPER(TRIM(D35)) -> Mary | F35: Female | G35: 130 | H35: =IF(AND(G35>18, G35<65), "Valid", "Invalid") -> Invalid | I35: PH | J35: =PROPER(TRIM(I35)) -> Ph | K35: Beauty | L35: =PROPER(TRIM(K35)) -> Beauty | M35: Cream | N35: =PROPER(TRIM(M35)) -> Cream | O35: 402.37 | P35: 10 | Q35: =IF(P35<1, 1, P35) -> 10 | R35: 0 | S35: =IF(OR(R35<0,R35>100),"invalid","Valid") -> Valid | T35: Transfer | U35: =PROPER(TRIM(T35)) -> Transfer | V35: Dan | W35: =PROPER(TRIM(V35)) -> Dan | X35: South | Y35: 4 | Z35: =IF(D35="", "Missing", "ok") -> ok | AA35: =(O35*Q35)*(1-R35/100) -> 4023.7
A36: T100036 | B36: 2025-12-30 | C36: C1794 | D36: Grace | E36: =PROPER(TRIM(D36)) -> Grace | F36: Male | G36: 19 | H36: =IF(AND(G36>18, G36<65), "Valid", "Invalid") -> Valid | I36: LAGOS | J36: =PROPER(TRIM(I36)) -> Lagos | K36: Home | L36: =PROPER(TRIM(K36)) -> Home | M36: Chair | N36: =PROPER(TRIM(M36)) -> Chair | O36: 489.41 | P36: 1 | Q36: =IF(P36<1, 1, P36) -> 1 | R36: 0 | S36: =IF(OR(R36<0,R36>100),"invalid","Valid") -> Valid | T36: Transfer | U36: =PROPER(TRIM(T36)) -> Transfer | V36: Chi | W36: =PROPER(TRIM(V36)) -> Chi | X36: South | Y36: 3 | Z36: =IF(D36="", "Missing", "ok") -> ok | AA36: =(O36*Q36)*(1-R36/100) -> 489.41
A37: T100037 | B37: 2025-11-16 | C37: C3074 | D37: John | E37: =PROPER(TRIM(D37)) -> John | F37: Female | G37: 64 | H37: =IF(AND(G37>18, G37<65), "Valid", "Invalid") -> Valid | I37: LAGOS | J37: =PROPER(TRIM(I37)) -> Lagos | K37: Fashion | L37: =PROPER(TRIM(K37)) -> Fashion | M37: Shirt | N37: =PROPER(TRIM(M37)) -> Shirt | O37: 203.77 | P37: 9 | Q37: =IF(P37<1, 1, P37) -> 9 | R37: 120 | S37: =IF(OR(R37<0,R37>100),"invalid","Valid") -> invalid | T37: Transfer | U37: =PROPER(TRIM(T37)) -> Transfer | V37: Chi | W37: =PROPER(TRIM(V37)) -> Chi | X37: South | Y37: 3 | Z37: =IF(D37="", "Missing", "ok") -> ok | AA37: =(O37*Q37)*(1-R37/100) -> -366.786
A38: T100038 | B38: 2025-07-10 | C38: C2121 | D38: James | E38: =PROPER(TRIM(D38)) -> James | F38: Female | G38: 8 | H38: =IF(AND(G38>18, G38<65), "Valid", "Invalid") -> Invalid | I38: PH | J38: =PROPER(TRIM(I38)) -> Ph | K38: Sports | L38: =PROPER(TRIM(K38)) -> Sports | M38: Ball | N38: =PROPER(TRIM(M38)) -> Ball | O38: 333.17 | P38: 8 | Q38: =IF(P38<1, 1, P38) -> 8 | R38: -10 | S38: =IF(OR(R38<0,R38>100),"invalid","Valid") -> invalid | T38: Cash | U38: =PROPER(TRIM(T38)) -> Cash | V38: Ada | W38: =PROPER(TRIM(V38)) -> Ada | X38: South | Y38: 4 | Z38: =IF(D38="", "Missing", "ok") -> ok | AA38: =(O38*Q38)*(1-R38/100) -> 2931.896
A39: T100039 | B39: 2025-12-11 | C39: C5675 | D39: John | E39: =PROPER(TRIM(D39)) -> John | F39: Female | G39: 130 | H39: =IF(AND(G39>18, G39<65), "Valid", "Invalid") -> Invalid | I39: Kano | J39: =PROPER(TRIM(I39)) -> Kano | K39: Home | L39: =PROPER(TRIM(K39)) -> Home | M39: Chair | N39: =PROPER(TRIM(M39)) -> Chair | O39: 166.86 | P39: -2 | Q39: =IF(P39<1, 1, P39) -> 1 | R39: 5 | S39: =IF(OR(R39<0,R39>100),"invalid","Valid") -> Valid | T39: Mobile Money | U39: =PROPER(TRIM(T39)) -> Mobile Money | V39: Chi | W39: =PROPER(TRIM(V39)) -> Chi | X39: South | Y39: 3 | Z39: =IF(D39="", "Missing", "ok") -> ok | AA39: =(O39*Q39)*(1-R39/100) -> 158.517
A40: T100040 | B40: 2025-01-28 | C40: C5040 | D40: John | E40: =PROPER(TRIM(D40)) -> John | F40: Female | G40: 19 | H40: =IF(AND(G40>18, G40<65), "Valid", "Invalid") -> Valid | I40: Kano | J40: =PROPER(TRIM(I40)) -> Kano | K40: Beauty | L40: =PROPER(TRIM(K40)) -> Beauty | M40: Cream | N40: =PROPER(TRIM(M40)) -> Cream | O40: 442.23 | P40: -2 | Q40: =IF(P40<1, 1, P40) -> 1 | R40: 120 | S40: =IF(OR(R40<0,R40>100),"invalid","Valid") -> invalid | T40: POS | U40: =PROPER(TRIM(T40)) -> Pos | V40: Chi | W40: =PROPER(TRIM(V40)) -> Chi | X40: South | Y40: 1 | Z40: =IF(D40="", "Missing", "ok") -> ok | AA40: =(O40*Q40)*(1-R40/100) -> -88.446
A41: T100041 | B41: 2025-10-13 | C41: C4744 | D41: James | E41: =PROPER(TRIM(D41)) -> James | F41: Male | G41: 8 | H41: =IF(AND(G41>18, G41<65), "Valid", "Invalid") -> Invalid | I41: Kano | J41: =PROPER(TRIM(I41)) -> Kano | K41: groceris | L41: =PROPER(TRIM(K41)) -> Groceris | M41: Rice | N41: =PROPER(TRIM(M41)) -> Rice | O41: 189.02 | P41: 7 | Q41: =IF(P41<1, 1, P41) -> 7 | R41: 5 | S41: =IF(OR(R41<0,R41>100),"invalid","Valid") -> Valid | T41: Mobile Money | U41: =PROPER(TRIM(T41)) -> Mobile Money | V41: Ben | W41: =PROPER(TRIM(V41)) -> Ben | X41: West | Y41: 2 | Z41: =IF(D41="", "Missing", "ok") -> ok | AA41: =(O41*Q41)*(1-R41/100) -> 1256.983
A42: T100042 | B42: 25/11/2025 | C42: C8128 | D42: David | E42: =PROPER(TRIM(D42)) -> David | F42: Male | G42: 55 | H42: =IF(AND(G42>18, G42<65), "Valid", "Invalid") -> Valid | I42: Abuja | J42: =PROPER(TRIM(I42)) -> Abuja | K42: groceris | L42: =PROPER(TRIM(K42)) -> Groceris | M42: Rice | N42: =PROPER(TRIM(M42)) -> Rice | O42: 393.19 | P42: 3 | Q42: =IF(P42<1, 1, P42) -> 3 | R42: -10 | S42: =IF(OR(R42<0,R42>100),"invalid","Valid") -> invalid | T42: Cash | U42: =PROPER(TRIM(T42)) -> Cash | V42: Ben | W42: =PROPER(TRIM(V42)) -> Ben | X42: West | Y42: 5 | Z42: =IF(D42="", "Missing", "ok") -> ok | AA42: =(O42*Q42)*(1-R42/100) -> 1297.527
... A46: T100046 | B46: 2025-06-23 | C46: C5447 | D46: James | E46: =PROPER(TRIM(D46)) -> James | F46: Male | G46: 8 | H46: =IF(AND(G46>18, G46<65), "Valid", "Invalid") -> Invalid | I46: Kano | J46: =PROPER(TRIM(I46)) -> Kano | K46: Fashion | L46: =PROPER(TRIM(K46)) -> Fashion | M46: Shirt | N46: =PROPER(TRIM(M46)) -> Shirt | O46: 208.01 | P46: -2 | Q46: =IF(P46<1, 1, P46) -> 1 | R46: 120 | S46: =IF(OR(R46<0,R46>100),"invalid","Valid") -> invalid | T46: Mobile Money | U46: =PROPER(TRIM(T46)) -> Mobile Money | V46: Chi | W46: =PROPER(TRIM(V46)) -> Chi | X46: North | Y46: 3 | Z46: =IF(D46="", "Missing", "ok") -> ok | AA46: =(O46*Q46)*(1-R46/100) -> -41.602
A47: T100047 | B47: 2025-12-09 | C47: C4617 | D47: Aisha | E47: =PROPER(TRIM(D47)) -> Aisha | F47: Female | G47: 35 | H47: =IF(AND(G47>18, G47<65), "Valid", "Invalid") -> Valid | I47: LAGOS | J47: =PROPER(TRIM(I47)) -> Lagos | K47: Fashion | L47: =PROPER(TRIM(K47)) -> Fashion | M47: Shirt | N47: =PROPER(TRIM(M47)) -> Shirt | O47: 81.69 | P47: 5 | Q47: =IF(P47<1, 1, P47) -> 5 | R47: 10 | S47: =IF(OR(R47<0,R47>100),"invalid","Valid") -> Valid | U47: =PROPER(TRIM(T47)) | V47: Chi | W47: =PROPER(TRIM(V47)) -> Chi | X47: South | Y47: 5 | Z47: =IF(D47="", "Missing", "ok") -> ok | AA47: =(O47*Q47)*(1-R47/100) -> 367.605
A48: T100048 | B48: 2025-08-10 | C48: C8875 | D48: Peter | E48: =PROPER(TRIM(D48)) -> Peter | F48: Female | G48: 31 | H48: =IF(AND(G48>18, G48<65), "Valid", "Invalid") -> Valid | I48: Enugu | J48: =PROPER(TRIM(I48)) -> Enugu | K48: Fashion | L48: =PROPER(TRIM(K48)) -> Fashion | M48: Shirt | N48: =PROPER(TRIM(M48)) -> Shirt | O48: 259.49 | P48: 10 | Q48: =IF(P48<1, 1, P48) -> 10 | R48: 5 | S48: =IF(OR(R48<0,R48>100),"invalid","Valid") -> Valid | T48: POS | U48: =PROPER(TRIM(T48)) -> Pos | V48: Dan | W48: =PROPER(TRIM(V48)) -> Dan | X48: North | Z48: =IF(D48="", "Missing", "ok") -> ok | AA48: =(O48*Q48)*(1-R48/100) -> 2465.155
A49: T100049 | B49: 08/03/2025 | C49: C9888 | D49: Aisha | E49: =PROPER(TRIM(D49)) -> Aisha | F49: Female | G49: 130 | H49: =IF(AND(G49>18, G49<65), "Valid", "Invalid") -> Invalid | I49: Lagos | J49: =PROPER(TRIM(I49)) -> Lagos | K49: Fashion | L49: =PROPER(TRIM(K49)) -> Fashion | M49: Shirt | N49: =PROPER(TRIM(M49)) -> Shirt | O49: 314.5 | P49: -2 | Q49: =IF(P49<1, 1, P49) -> 1 | R49: 0 | S49: =IF(OR(R49<0,R49>100),"invalid","Valid") -> Valid | T49: Transfer | U49: =PROPER(TRIM(T49)) -> Transfer | V49: Ada | W49: =PROPER(TRIM(V49)) -> Ada | X49: West | Y49: 1 | Z49: =IF(D49="", "Missing", "ok") -> ok | AA49: =(O49*Q49)*(1-R49/100) -> 314.5
A50: T100050 | B50: 2026-05-13 | C50: C1503 | D50: Aisha | E50: =PROPER(TRIM(D50)) -> Aisha | F50: Female | G50: 43 | H50: =IF(AND(G50>18, G50<65), "Valid", "Invalid") -> Valid | I50: LAGOS | J50: =PROPER(TRIM(I50)) -> Lagos | K50: Beauty | L50: =PROPER(TRIM(K50)) -> Beauty | M50: Cream | N50: =PROPER(TRIM(M50)) -> Cream | O50: 55.24 | P50: -2 | Q50: =IF(P50<1, 1, P50) -> 1 | R50: 10 | S50: =IF(OR(R50<0,R50>100),"invalid","Valid") -> Valid | U50: =PROPER(TRIM(T50)) | V50: Dan | W50: =PROPER(TRIM(V50)) -> Dan | X50: West | Y50: 4 | Z50: =IF(D50="", "Missing", "ok") -> ok | AA50: =(O50*Q50)*(1-R50/100) -> 49.716
A51: T100051 | B51: 2025-10-08 | C51: C3078 | D51: Mary | E51: =PROPER(TRIM(D51)) -> Mary | F51: Male | G51: 8 | H51: =IF(AND(G51>18, G51<65), "Valid", "Invalid") -> Invalid | I51: Lagos | J51: =PROPER(TRIM(I51)) -> Lagos | K51: Sports | L51: =PROPER(TRIM(K51)) -> Sports | M51: Ball | N51: =PROPER(TRIM(M51)) -> Ball | O51: 69.56 | P51: -2 | Q51: =IF(P51<1, 1, P51) -> 1 | R51: 0 | S51: =IF(OR(R51<0,R51>100),"invalid","Valid") -> Valid | T51: POS | U51: =PROPER(TRIM(T51)) -> Pos | V51: Ben | W51: =PROPER(TRIM(V51)) -> Ben | X51: East | Y51: 4 | Z51: =IF(D51="", "Missing", "ok") -> ok | AA51: =(O51*Q51)*(1-R51/100) -> 69.56
A52: T100052 | B52: 2026-01-16 | C52: C5288 | D52: David | E52: =PROPER(TRIM(D52)) -> David | F52: Female | G52: 38 | H52: =IF(AND(G52>18, G52<65), "Valid", "Invalid") -> Valid | I52: lagos | J52: =PROPER(TRIM(I52)) -> Lagos | K52: Electronics | L52: =PROPER(TRIM(K52)) -> Electronics | M52: Phone | N52: =PROPER(TRIM(M52)) -> Phone | O52: 251.91 | P52: 2 | Q52: =IF(P52<1, 1, P52) -> 2 | R52: -10 | S52: =IF(OR(R52<0,R52>100),"invalid","Valid") -> invalid | T52: POS | U52: =PROPER(TRIM(T52)) -> Pos | V52: Dan | W52: =PROPER(TRIM(V52)) -> Dan | X52: North | Y52: 2 | Z52: =IF(D52="", "Missing", "ok") -> ok | AA52: =(O52*Q52)*(1-R52/100) -> 554.202
A53: T100053 | B53: 2025-06-13 | C53: C6608 | D53: James | E53: =PROPER(TRIM(D53)) -> James | F53: Male | G53: 130 | H53: =IF(AND(G53>18, G53<65), "Valid", "Invalid") -> Invalid | I53: Lagos | J53: =PROPER(TRIM(I53)) -> Lagos | K53: groceris | L53: =PROPER(TRIM(K53)) -> Groceris | M53: Rice | N53: =PROPER(TRIM(M53)) -> Rice | O53: 45.83 | P53: 10 | Q53: =IF(P53<1, 1, P53) -> 10 | R53: 5 | S53: =IF(OR(R53<0,R53>100),"invalid","Valid") -> Valid | U53: =PROPER(TRIM(T53)) | V53: Chi | W53: =PROPER(TRIM(V53)) -> Chi | X53: East | Y53: 5 | Z53: =IF(D53="", "Missing", "ok") -> ok | AA53: =(O53*Q53)*(1-R53/100) -> 435.385
A54: T100054 | B54: 2025-07-03 | C54: C4525 | E54: =PROPER(TRIM(D54)) | F54: Male | G54: 130 | H54: =IF(AND(G54>18, G54<65), "Valid", "Invalid") -> Invalid | I54: lagos | J54: =PROPER(TRIM(I54)) -> Lagos | K54: Sports | L54: =PROPER(TRIM(K54)) -> Sports | M54: Ball | N54: =PROPER(TRIM(M54)) -> Ball | O54: 296.27 | P54: -2 | Q54: =IF(P54<1, 1, P54) -> 1 | R54: 10 | S54: =IF(OR(R54<0,R54>100),"invalid","Valid") -> Valid | T54: Transfer | U54: =PROPER(TRIM(T54)) -> Transfer | V54: Ada | W54: =PROPER(TRIM(V54)) -> Ada | X54: West | Y54: 3 | Z54: =IF(D54="", "Missing", "ok") -> Missing | AA54: =(O54*Q54)*(1-R54/100) -> 266.643
A55: T100055 | B55: 2025-01-11 | C55: C7424 | D55: Peter | E55: =PROPER(TRIM(D55)) -> Peter | F55: Female | G55: 8 | H55: =IF(AND(G55>18, G55<65), "Valid", "Invalid") -> Invalid | I55: Kano | J55: =PROPER(TRIM(I55)) -> Kano | K55: Home | L55: =PROPER(TRIM(K55)) -> Home | M55: Chair | N55: =PROPER(TRIM(M55)) -> Chair | O55: 5.33 | P55: -2 | Q55: =IF(P55<1, 1, P55) -> 1 | R55: -10 | S55: =IF(OR(R55<0,R55>100),"invalid","Valid") -> invalid | T55: Cash | U55: =PROPER(TRIM(T55)) -> Cash | V55: Ben | W55: =PROPER(TRIM(V55)) -> Ben | X55: South | Y55: 4 | Z55: =IF(D55="", "Missing", "ok") -> ok | AA55: =(O55*Q55)*(1-R55/100) -> 5.863
A56: T100056 | B56: 14/05/2026 | C56: C2827 | E56: =PROPER(TRIM(D56)) | F56: Female | G56: 8 | H56: =IF(AND(G56>18, G56<65), "Valid", "Invalid") -> Invalid | I56: LAGOS | J56: =PROPER(TRIM(I56)) -> Lagos | K56: groceris | L56: =PROPER(TRIM(K56)) -> Groceris | M56: Rice | N56: =PROPER(TRIM(M56)) -> Rice | O56: 280.75 | P56: -2 | Q56: =IF(P56<1, 1, P56) -> 1 | R56: 5 | S56: =IF(OR(R56<0,R56>100),"invalid","Valid") -> Valid | T56: Transfer | U56: =PROPER(TRIM(T56)) -> Transfer | V56: Ben | W56: =PROPER(TRIM(V56)) -> Ben | X56: East | Y56: 3 | Z56: =IF(D56="", "Missing", "ok") -> Missing | AA56: =(O56*Q56)*(1-R56/100) -> 266.7125
A57: T100057 | B57: 2025-04-17 | C57: C1406 | D57: David | E57: =PROPER(TRIM(D57)) -> David | F57: Male | G57: 50 | H57: =IF(AND(G57>18, G57<65), "Valid", "Invalid") -> Valid | I57: lagos | J57: =PROPER(TRIM(I57)) -> Lagos | K57: Sports | L57: =PROPER(TRIM(K57)) -> Sports | M57: Ball | N57: =PROPER(TRIM(M57)) -> Ball | O57: 14.25 | P57: 7 | Q57: =IF(P57<1, 1, P57) -> 7 | R57: 5 | S57: =IF(OR(R57<0,R57>100),"invalid","Valid") -> Valid | T57: Mobile Money | U57: =PROPER(TRIM(T57)) -> Mobile Money | V57: Dan | W57: =PROPER(TRIM(V57)) -> Dan | X57: West | Y57: 3 | Z57: =IF(D57="", "Missing", "ok") -> ok | AA57: =(O57*Q57)*(1-R57/100) -> 94.7625
A58: T100058 | B58: 2025-06-19 | C58: C5616 | D58: John | E58: =PROPER(TRIM(D58)) -> John | F58: Male | G58: 43 | H58: =IF(AND(G58>18, G58<65), "Valid", "Invalid") -> Valid | I58: Abuja | J58: =PROPER(TRIM(I58)) -> Abuja | K58: Fashion | L58: =PROPER(TRIM(K58)) -> Fashion | M58: Shirt | N58: =PROPER(TRIM(M58)) -> Shirt | O58: 372.98 | P58: -2 | Q58: =IF(P58<1, 1, P58) -> 1 | R58: 15 | S58: =IF(OR(R58<0,R58>100),"invalid","Valid") -> Valid | T58: POS | U58: =PROPER(TRIM(T58)) -> Pos | V58: Dan | W58: =PROPER(TRIM(V58)) -> Dan | X58: South | Z58: =IF(D58="", "Missing", "ok") -> ok | AA58: =(O58*Q58)*(1-R58/100) -> 317.033
A59: T100059 | B59: 2025-04-08 | C59: C3581 | D59: Grace | E59: =PROPER(TRIM(D59)) -> Grace | F59: Male | G59: 8 | H59: =IF(AND(G59>18, G59<65), "Valid", "Invalid") -> Invalid | I59: Lagos | J59: =PROPER(TRIM(I59)) -> Lagos | K59: groceris | L59: =PROPER(TRIM(K59)) -> Groceris | M59: Rice | N59: =PROPER(TRIM(M59)) -> Rice | O59: 98.86 | P59: 9 | Q59: =IF(P59<1, 1, P59) -> 9 | R59: 120 | S59: =IF(OR(R59<0,R59>100),"invalid","Valid") -> invalid | T59: POS | U59: =PROPER(TRIM(T59)) -> Pos | V59: Dan | W59: =PROPER(TRIM(V59)) -> Dan | X59: North | Y59: 5 | Z59: =IF(D59="", "Missing", "ok") -> ok | AA59: =(O59*Q59)*(1-R59/100) -> -177.948
A60: T100060 | B60: 2026-04-17 | C60: C7298 | D60: James | E60: =PROPER(TRIM(D60)) -> James | F60: Male | G60: 8 | H60: =IF(AND(G60>18, G60<65), "Valid", "Invalid") -> Invalid | I60: Lagos | J60: =PROPER(TRIM(I60)) -> Lagos | K60: Groceries | L60: =PROPER(TRIM(K60)) -> Groceries | M60: Rice | N60: =PROPER(TRIM(M60)) -> Rice | O60: 481.05 | P60: 2 | Q60: =IF(P60<1, 1, P60) -> 2 | R60: 0 | S60: =IF(OR(R60<0,R60>100),"invalid","Valid") -> Valid | U60: =PROPER(TRIM(T60)) | V60: Chi | W60: =PROPER(TRIM(V60)) -> Chi | X60: North | Y60: 1 | Z60: =IF(D60="", "Missing", "ok") -> ok | AA60: =(O60*Q60)*(1-R60/100) -> 962.1
A61: T100061 | B61: 2026-05-21 | C61: C2137 | E61: =PROPER(TRIM(D61)) | F61: Male | G61: 41 | H61: =IF(AND(G61>18, G61<65), "Valid", "Invalid") -> Valid | I61: lagos | J61: =PROPER(TRIM(I61)) -> Lagos | K61: groceris | L61: =PROPER(TRIM(K61)) -> Groceris | M61: Rice | N61: =PROPER(TRIM(M61)) -> Rice | O61: 172.45 | P61: -2 | Q61: =IF(P61<1, 1, P61) -> 1 | R61: 10 | S61: =IF(OR(R61<0,R61>100),"invalid","Valid") -> Valid | T61: Transfer | U61: =PROPER(TRIM(T61)) -> Transfer | V61: Dan | W61: =PROPER(TRIM(V61)) -> Dan | X61: East | Y61: 1 | Z61: =IF(D61="", "Missing", "ok") -> Missing | AA61: =(O61*Q61)*(1-R61/100) -> 155.205
A62: T100062 | B62: 2025-11-28 | C62: C5849 | E62: =PROPER(TRIM(D62)) | F62: Female | G62: 52 | H62: =IF(AND(G62>18, G62<65), "Valid", "Invalid") -> Valid | I62: lagos | J62: =PROPER(TRIM(I62)) -> Lagos | K62: Beauty | L62: =PROPER(TRIM(K62)) -> Beauty | M62: Cream | N62: =PROPER(TRIM(M62)) -> Cream | O62: 308.43 | P62: -2 | Q62: =IF(P62<1, 1, P62) -> 1 | R62: 5 | S62: =IF(OR(R62<0,R62>100),"invalid","Valid") -> Valid | T62: Cash | U62: =PROPER(TRIM(T62)) -> Cash | V62: Ben | W62: =PROPER(TRIM(V62)) -> Ben | X62: West | Y62: 3 | Z62: =IF(D62="", "Missing", "ok") -> Missing | AA62: =(O62*Q62)*(1-R62/100) -> 293.0085
A63: T100063 | B63: 02/07/2025 | C63: C7933 | D63: Mary | E63: =PROPER(TRIM(D63)) -> Mary | F63: Male | G63: 29 | H63: =IF(AND(G63>18, G63<65), "Valid", "Invalid") -> Valid | I63: Enugu | J63: =PROPER(TRIM(I63)) -> Enugu | K63: Electronics | L63: =PROPER(TRIM(K63)) -> Electronics | M63: Phone | N63: =PROPER(TRIM(M63)) -> Phone | O63: 239.81 | P63: 10 | Q63: =IF(P63<1, 1, P63) -> 10 | R63: 15 | S63: =IF(OR(R63<0,R63>100),"invalid","Valid") -> Valid | T63: Transfer | U63: =PROPER(TRIM(T63)) -> Transfer | V63: Ada | W63: =PROPER(TRIM(V63)) -> Ada | X63: East | Y63: 4 | Z63: =IF(D63="", "Missing", "ok") -> ok | AA63: =(O63*Q63)*(1-R63/100) -> 2038.385
A64: T100064 | B64: 2025-06-16 | C64: C3249 | D64: James | E64: =PROPER(TRIM(D64)) -> James | F64: Female | G64: 43 | H64: =IF(AND(G64>18, G64<65), "Valid", "Invalid") -> Valid | I64: PH | J64: =PROPER(TRIM(I64)) -> Ph | K64: Home | L64: =PROPER(TRIM(K64)) -> Home | M64: Chair | N64: =PROPER(TRIM(M64)) -> Chair | O64: 12.92 | P64: 10 | Q64: =IF(P64<1, 1, P64) -> 10 | R64: 10 | S64: =IF(OR(R64<0,R64>100),"invalid","Valid") -> Valid | T64: Transfer | U64: =PROPER(TRIM(T64)) -> Transfer | V64: Dan | W64: =PROPER(TRIM(V64)) -> Dan | X64: West | Y64: 4 | Z64: =IF(D64="", "Missing", "ok") -> ok | AA64: =(O64*Q64)*(1-R64/100) -> 116.28
A65: T100065 | B65: 2025-07-21 | C65: C3400 | E65: =PROPER(TRIM(D65)) | F65: Male | G65: 130 | H65: =IF(AND(G65>18, G65<65), "Valid", "Invalid") -> Invalid | I65: Abuja | J65: =PROPER(TRIM(I65)) -> Abuja | K65: Home | L65: =PROPER(TRIM(K65)) -> Home | M65: Chair | N65: =PROPER(TRIM(M65)) -> Chair | O65: 381.75 | P65: -2 | Q65: =IF(P65<1, 1, P65) -> 1 | R65: 5 | S65: =IF(OR(R65<0,R65>100),"invalid","Valid") -> Valid | U65: =PROPER(TRIM(T65)) | V65: Ben | W65: =PROPER(TRIM(V65)) -> Ben | X65: West | Z65: =IF(D65="", "Missing", "ok") -> Missing | AA65: =(O65*Q65)*(1-R65/100) -> 362.6625
A66: T100066 | B66: 2025-06-20 | C66: C7913 | D66: Aisha | E66: =PROPER(TRIM(D66)) -> Aisha | F66: Female | G66: 54 | H66: =IF(AND(G66>18, G66<65), "Valid", "Invalid") -> Valid | I66: lagos | J66: =PROPER(TRIM(I66)) -> Lagos | K66: groceris | L66: =PROPER(TRIM(K66)) -> Groceris | M66: Rice | N66: =PROPER(TRIM(M66)) -> Rice | O66: 481.13 | P66: 7 | Q66: =IF(P66<1, 1, P66) -> 7 | R66: 15 | S66: =IF(OR(R66<0,R66>100),"invalid","Valid") -> Valid | T66: Cash | U66: =PROPER(TRIM(T66)) -> Cash | V66: Ada | W66: =PROPER(TRIM(V66)) -> Ada | X66: South | Y66: 4 | Z66: =IF(D66="", "Missing", "ok") -> ok | AA66: =(O66*Q66)*(1-R66/100) -> 2862.7235
A67: T100067 | B67: 2026-06-23 | C67: C2685 | D67: Grace | E67: =PROPER(TRIM(D67)) -> Grace | F67: Female | G67: 130 | H67: =IF(AND(G67>18, G67<65), "Valid", "Invalid") -> Invalid | I67: lagos | J67: =PROPER(TRIM(I67)) -> Lagos | K67: Fashion | L67: =PROPER(TRIM(K67)) -> Fashion | M67: Shirt | N67: =PROPER(TRIM(M67)) -> Shirt | O67: 141.11 | P67: -2 | Q67: =IF(P67<1, 1, P67) -> 1 | R67: 0 | S67: =IF(OR(R67<0,R67>100),"invalid","Valid") -> Valid | T67: Cash | U67: =PROPER(TRIM(T67)) -> Cash | V67: Dan | W67: =PROPER(TRIM(V67)) -> Dan | X67: South | Z67: =IF(D67="", "Missing", "ok") -> ok | AA67: =(O67*Q67)*(1-R67/100) -> 141.11
A68: T100068 | B68: 2026-01-19 | C68: C6284 | D68: John | E68: =PROPER(TRIM(D68)) -> John | F68: Male | G68: 29 | H68: =IF(AND(G68>18, G68<65), "Valid", "Invalid") -> Valid | I68: PH | J68: =PROPER(TRIM(I68)) -> Ph | K68: groceris | L68: =PROPER(TRIM(K68)) -> Groceris | M68: Rice | N68: =PROPER(TRIM(M68)) -> Rice | O68: 137.34 | P68: 10 | Q68: =IF(P68<1, 1, P68) -> 10 | R68: 5 | S68: =IF(OR(R68<0,R68>100),"invalid","Valid") -> Valid | T68: POS | U68: =PROPER(TRIM(T68)) -> Pos | V68: Ada | W68: =PROPER(TRIM(V68)) -> Ada | X68: East | Y68: 3 | Z68: =IF(D68="", "Missing", "ok") -> ok | AA68: =(O68*Q68)*(1-R68/100) -> 1304.73
A69: T100069 | B69: 2026-06-03 | C69: C5459 | D69: Grace | E69: =PROPER(TRIM(D69)) -> Grace | F69: Female | G69: 130 | H69: =IF(AND(G69>18, G69<65), "Valid", "Invalid") -> Invalid | I69: Lagos | J69: =PROPER(TRIM(I69)) -> Lagos | K69: groceris | L69: =PROPER(TRIM(K69)) -> Groceris | M69: Rice | N69: =PROPER(TRIM(M69)) -> Rice | O69: 223.18 | P69: -2 | Q69: =IF(P69<1, 1, P69) -> 1 | R69: -10 | S69: =IF(OR(R69<0,R69>100),"invalid","Valid") -> invalid | T69: Transfer | U69: =PROPER(TRIM(T69)) -> Transfer | V69: Chi | W69: =PROPER(TRIM(V69)) -> Chi | X69: South | Y69: 2 | Z69: =IF(D69="", "Missing", "ok") -> ok | AA69: =(O69*Q69)*(1-R69/100) -> 245.498
A70: T100070 | B70: 27/10/2025 | C70: C3034 | E70: =PROPER(TRIM(D70)) | F70: Male | G70: 130 | H70: =IF(AND(G70>18, G70<65), "Valid", "Invalid") -> Invalid | I70: Enugu | J70: =PROPER(TRIM(I70)) -> Enugu | K70: Groceries | L70: =PROPER(TRIM(K70)) -> Groceries | M70: Rice | N70: =PROPER(TRIM(M70)) -> Rice | O70: 456.44 | P70: 3 | Q70: =IF(P70<1, 1, P70) -> 3 | R70: 0 | S70: =IF(OR(R70<0,R70>100),"invalid","Valid") -> Valid | U70: =PROPER(TRIM(T70)) | V70: Ada | W70: =PROPER(TRIM(V70)) -> Ada | X70: East | Y70: 3 | Z70: =IF(D70="", "Missing", "ok") -> Missing | AA70: =(O70*Q70)*(1-R70/100) -> 1369.32
A71: T100071 | B71: 2025-07-19 | C71: C9830 | D71: James | E71: =PROPER(TRIM(D71)) -> James | F71: Female | G71: 42 | H71: =IF(AND(G71>18, G71<65), "Valid", "Invalid") -> Valid | I71: Abuja | J71: =PROPER(TRIM(I71)) -> Abuja | K71: Home | L71: =PROPER(TRIM(K71)) -> Home | M71: Chair | N71: =PROPER(TRIM(M71)) -> Chair | O71: 159.08 | P71: -2 | Q71: =IF(P71<1, 1, P71) -> 1 | R71: 120 | S71: =IF(OR(R71<0,R71>100),"invalid","Valid") -> invalid | U71: =PROPER(TRIM(T71)) | V71: Ben | W71: =PROPER(TRIM(V71)) -> Ben | X71: North | Z71: =IF(D71="", "Missing", "ok") -> ok | AA71: =(O71*Q71)*(1-R71/100) -> -31.816
A72: T100072 | B72: 2025-01-20 | C72: C4142 | D72: Grace | E72: =PROPER(TRIM(D72)) -> Grace | F72: Male | G72: 130 | H72: =IF(AND(G72>18, G72<65), "Valid", "Invalid") -> Invalid | I72: PH | J72: =PROPER(TRIM(I72)) -> Ph | K72: Beauty | L72: =PROPER(TRIM(K72)) -> Beauty | M72: Cream | N72: =PROPER(TRIM(M72)) -> Cream | O72: 328.53 | P72: -2 | Q72: =IF(P72<1, 1, P72) -> 1 | R72: -10 | S72: =IF(OR(R72<0,R72>100),"invalid","Valid") -> invalid | U72: =PROPER(TRIM(T72)) | V72: Ada | W72: =PROPER(TRIM(V72)) -> Ada | X72: East | Y72: 3 | Z72: =IF(D72="", "Missing", "ok") -> ok | AA72: =(O72*Q72)*(1-R72/100) -> 361.383
A73: T100073 | B73: 2025-09-29 | C73: C7135 | D73: John | E73: =PROPER(TRIM(D73)) -> John | F73: Male | G73: 130 | H73: =IF(AND(G73>18, G73<65), "Valid", "Invalid") -> Invalid | I73: PH | J73: =PROPER(TRIM(I73)) -> Ph | K73: Electronics | L73: =PROPER(TRIM(K73)) -> Electronics | M73: Phone | N73: =PROPER(TRIM(M73)) -> Phone | O73: 223.95 | P73: -2 | Q73: =IF(P73<1, 1, P73) -> 1 | R73: 0 | S73: =IF(OR(R73<0,R73>100),"invalid","Valid") -> Valid | T73: Mobile Money | U73: =PROPER(TRIM(T73)) -> Mobile Money | V73: Chi | W73: =PROPER(TRIM(V73)) -> Chi | X73: South | Y73: 3 | Z73: =IF(D73="", "Missing", "ok") -> ok | AA73: =(O73*Q73)*(1-R73/100) -> 223.95
A74: T100074 | B74: 2025-03-20 | C74: C9233 | D74: Grace | E74: =PROPER(TRIM(D74)) -> Grace | F74: Female | G74: 130 | H74: =IF(AND(G74>18, G74<65), "Valid", "Invalid") -> Invalid | I74: Enugu | J74: =PROPER(TRIM(I74)) -> Enugu | K74: Fashion | L74: =PROPER(TRIM(K74)) -> Fashion | M74: Shirt | N74: =PROPER(TRIM(M74)) -> Shirt | O74: 100.23 | P74: -2 | Q74: =IF(P74<1, 1, P74) -> 1 | R74: 120 | S74: =IF(OR(R74<0,R74>100),"invalid","Valid") -> invalid | T74: Transfer | U74: =PROPER(TRIM(T74)) -> Transfer | V74: Ada | W74: =PROPER(TRIM(V74)) -> Ada | X74: South | Y74: 1 | Z74: =IF(D74="", "Missing", "ok") -> ok | AA74: =(O74*Q74)*(1-R74/100) -> -20.046
A75: T100075 | B75: 2025-11-09 | C75: C7805 | D75: James | E75: =PROPER(TRIM(D75)) -> James | F75: Female | G75: 36 | H75: =IF(AND(G75>18, G75<65), "Valid", "Invalid") -> Valid | I75: Enugu | J75: =PROPER(TRIM(I75)) -> Enugu | K75: Home | L75: =PROPER(TRIM(K75)) -> Home | M75: Chair | N75: =PROPER(TRIM(M75)) -> Chair | O75: 288.64 | P75: 1 | Q75: =IF(P75<1, 1, P75) -> 1 | R75: 120 | S75: =IF(OR(R75<0,R75>100),"invalid","Valid") -> invalid | T75: Mobile Money | U75: =PROPER(TRIM(T75)) -> Mobile Money | V75: Ada | W75: =PROPER(TRIM(V75)) -> Ada | X75: East | Y75: 5 | Z75: =IF(D75="", "Missing", "ok") -> ok | AA75: =(O75*Q75)*(1-R75/100) -> -57.728
A76: T100076 | B76: 2025-05-13 | C76: C2098 | D76: David | E76: =PROPER(TRIM(D76)) -> David | F76: Female | G76: 130 | H76: =IF(AND(G76>18, G76<65), "Valid", "Invalid") -> Invalid | I76: Abuja | J76: =PROPER(TRIM(I76)) -> Abuja | K76: Electronics | L76: =PROPER(TRIM(K76)) -> Electronics | M76: Phone | N76: =PROPER(TRIM(M76)) -> Phone | O76: 84.9 | P76: -2 | Q76: =IF(P76<1, 1, P76) -> 1 | R76: 5 | S76: =IF(OR(R76<0,R76>100),"invalid","Valid") -> Valid | T76: Mobile Money | U76: =PROPER(TRIM(T76)) -> Mobile Money | V76: Chi | W76: =PROPER(TRIM(V76)) -> Chi | X76: West | Y76: 3 | Z76: =IF(D76="", "Missing", "ok") -> ok | AA76: =(O76*Q76)*(1-R76/100) -> 80.655
A77: T100077 | B77: 29/12/2025 | C77: C2806 | D77: Peter | E77: =PROPER(TRIM(D77)) -> Peter | F77: Male | G77: 21 | H77: =IF(AND(G77>18, G77<65), "Valid", "Invalid") -> Valid | I77: LAGOS | J77: =PROPER(TRIM(I77)) -> Lagos | K77: Beauty | L77: =PROPER(TRIM(K77)) -> Beauty | M77: Cream | N77: =PROPER(TRIM(M77)) -> Cream | O77: 105.76 | P77: 6 | Q77: =IF(P77<1, 1, P77) -> 6 | R77: 5 | S77: =IF(OR(R77<0,R77>100),"invalid","Valid") -> Valid | U77: =PROPER(TRIM(T77)) | V77: Chi | W77: =PROPER(TRIM(V77)) -> Chi | X77: West | Y77: 3 | Z77: =IF(D77="", "Missing", "ok") -> ok | AA77: =(O77*Q77)*(1-R77/100) -> 602.832
A78: T100078 | B78: 2025-04-06 | C78: C2788 | D78: David | E78: =PROPER(TRIM(D78)) -> David | F78: Female | G78: 44 | H78: =IF(AND(G78>18, G78<65), "Valid", "Invalid") -> Valid | I78: LAGOS | J78: =PROPER(TRIM(I78)) -> Lagos | K78: Beauty | L78: =PROPER(TRIM(K78)) -> Beauty | M78: Cream | N78: =PROPER(TRIM(M78)) -> Cream | O78: 229.49 | P78: -2 | Q78: =IF(P78<1, 1, P78) -> 1 | R78: -10 | S78: =IF(OR(R78<0,R78>100),"invalid","Valid") -> invalid | T78: POS | U78: =PROPER(TRIM(T78)) -> Pos | V78: Ben | W78: =PROPER(TRIM(V78)) -> Ben | X78: South | Y78: 3 | Z78: =IF(D78="", "Missing", "ok") -> ok | AA78: =(O78*Q78)*(1-R78/100) -> 252.439
A79: T100079 | B79: 2026-01-21 | C79: C6728 | D79: Peter | E79: =PROPER(TRIM(D79)) -> Peter | F79: Female | G79: 8 | H79: =IF(AND(G79>18, G79<65), "Valid", "Invalid") -> Invalid | I79: LAGOS | J79: =PROPER(TRIM(I79)) -> Lagos | K79: Electronics | L79: =PROPER(TRIM(K79)) -> Electronics | M79: Phone | N79: =PROPER(TRIM(M79)) -> Phone | O79: 297.94 | P79: -2 | Q79: =IF(P79<1, 1, P79) -> 1 | R79: -10 | S79: =IF(OR(R79<0,R79>100),"invalid","Valid") -> invalid | T79: Transfer | U79: =PROPER(TRIM(T79)) -> Transfer | V79: Chi | W79: =PROPER(TRIM(V79)) -> Chi | X79: East | Z79: =IF(D79="", "Missing", "ok") -> ok | AA79: =(O79*Q79)*(1-R79/100) -> 327.734
A80: T100080 | B80: 2025-04-23 | C80: C8672 | E80: =PROPER(TRIM(D80)) | F80: Female | G80: 33 | H80: =IF(AND(G80>18, G80<65), "Valid", "Invalid") -> Valid | I80: Kano | J80: =PROPER(TRIM(I80)) -> Kano | K80: Electronics | L80: =PROPER(TRIM(K80)) -> Electronics | M80: Phone | N80: =PROPER(TRIM(M80)) -> Phone | O80: 256.49 | P80: 10 | Q80: =IF(P80<1, 1, P80) -> 10 | R80: -10 | S80: =IF(OR(R80<0,R80>100),"invalid","Valid") -> invalid | T80: Mobile Money | U80: =PROPER(TRIM(T80)) -> Mobile Money | V80: Dan | W80: =PROPER(TRIM(V80)) -> Dan | X80: South | Y80: 4 | Z80: =IF(D80="", "Missing", "ok") -> Missing | AA80: =(O80*Q80)*(1-R80/100) -> 2821.39
A81: T100081 | B81: 2025-08-19 | C81: C9970 | D81: Mary | E81: =PROPER(TRIM(D81)) -> Mary | F81: Female | G81: 130 | H81: =IF(AND(G81>18, G81<65), "Valid", "Invalid") -> Invalid | I81: Kano | J81: =PROPER(TRIM(I81)) -> Kano | K81: Beauty | L81: =PROPER(TRIM(K81)) -> Beauty | M81: Cream | N81: =PROPER(TRIM(M81)) -> Cream | O81: 202.13 | P81: 2 | Q81: =IF(P81<1, 1, P81) -> 2 | R81: -10 | S81: =IF(OR(R81<0,R81>100),"invalid","Valid") -> invalid | T81: POS | U81: =PROPER(TRIM(T81)) -> Pos | V81: Dan | W81: =PROPER(TRIM(V81)) -> Dan | X81: South | Z81: =IF(D81="", "Missing", "ok") -> ok | AA81: =(O81*Q81)*(1-R81/100) -> 444.686
A82: T100082 | B82: 2025-11-08 | C82: C4583 | D82: Grace | E82: =PROPER(TRIM(D82)) -> Grace | F82: Female | G82: 130 | H82: =IF(AND(G82>18, G82<65), "Valid", "Invalid") -> Invalid | I82: Abuja | J82: =PROPER(TRIM(I82)) -> Abuja | K82: groceris | L82: =PROPER(TRIM(K82)) -> Groceris | M82: Rice | N82: =PROPER(TRIM(M82)) -> Rice | O82: 376.61 | P82: 2 | Q82: =IF(P82<1, 1, P82) -> 2 | R82: 15 | S82: =IF(OR(R82<0,R82>100),"invalid","Valid") -> Valid | T82: Mobile Money | U82: =PROPER(TRIM(T82)) -> Mobile Money | V82: Ben | W82: =PROPER(TRIM(V82)) -> Ben | X82: South | Y82: 2 | Z82: =IF(D82="", "Missing", "ok") -> ok | AA82: =(O82*Q82)*(1-R82/100) -> 640.237
A83: T100083 | B83: 2026-05-30 | C83: C9000 | D83: Grace | E83: =PROPER(TRIM(D83)) -> Grace | F83: Male | G83: 36 | H83: =IF(AND(G83>18, G83<65), "Valid", "Invalid") -> Valid | I83: LAGOS | J83: =PROPER(TRIM(I83)) -> Lagos | K83: Sports | L83: =PROPER(TRIM(K83)) -> Sports | M83: Ball | N83: =PROPER(TRIM(M83)) -> Ball | O83: 50.76 | P83: -2 | Q83: =IF(P83<1, 1, P83) -> 1 | R83: 120 | S83: =IF(OR(R83<0,R83>100),"invalid","Valid") -> invalid | T83: Mobile Money | U83: =PROPER(TRIM(T83)) -> Mobile Money | V83: Ben | W83: =PROPER(TRIM(V83)) -> Ben | X83: South | Y83: 2 | Z83: =IF(D83="", "Missing", "ok") -> ok | AA83: =(O83*Q83)*(1-R83/100) -> -10.152
A84: T100084 | B84: 28/06/2025 | C84: C5862 | D84: David | E84: =PROPER(TRIM(D84)) -> David | F84: Female | G84: 23 | H84: =IF(AND(G84>18, G84<65), "Valid", "Invalid") -> Valid | I84: Enugu | J84: =PROPER(TRIM(I84)) -> Enugu | K84: Home | L84: =PROPER(TRIM(K84)) -> Home | M84: Chair | N84: =PROPER(TRIM(M84)) -> Chair | O84: 164.1 | P84: 3 | Q84: =IF(P84<1, 1, P84) -> 3 | R84: 10 | S84: =IF(OR(R84<0,R84>100),"invalid","Valid") -> Valid | T84: POS | U84: =PROPER(TRIM(T84)) -> Pos | V84: Dan | W84: =PROPER(TRIM(V84)) -> Dan | X84: South | Y84: 3 | Z84: =IF(D84="", "Missing", "ok") -> ok | AA84: =(O84*Q84)*(1-R84/100) -> 443.07
A85: T100085 | B85: 2026-04-05 | C85: C8114 | D85: John | E85: =PROPER(TRIM(D85)) -> John | F85: Female | G85: 8 | H85: =IF(AND(G85>18, G85<65), "Valid", "Invalid") -> Invalid | I85: Lagos | J85: =PROPER(TRIM(I85)) -> Lagos | K85: Home | L85: =PROPER(TRIM(K85)) -> Home | M85: Chair | N85: =PROPER(TRIM(M85)) -> Chair | O85: 15.36 | P85: 4 | Q85: =IF(P85<1, 1, P85) -> 4 | R85: -10 | S85: =IF(OR(R85<0,R85>100),"invalid","Valid") -> invalid | T85: POS | U85: =PROPER(TRIM(T85)) -> Pos | V85: Ben | W85: =PROPER(TRIM(V85)) -> Ben | X85: North | Y85: 2 | Z85: =IF(D85="", "Missing", "ok") -> ok | AA85: =(O85*Q85)*(1-R85/100) -> 67.584
A86: T100086 | B86: 2025-06-03 | C86: C2837 | D86: David | E86: =PROPER(TRIM(D86)) -> David | F86: Male | G86: 63 | H86: =IF(AND(G86>18, G86<65), "Valid", "Invalid") -> Valid | I86: Kano | J86: =PROPER(TRIM(I86)) -> Kano | K86: Sports | L86: =PROPER(TRIM(K86)) -> Sports | M86: Ball | N86: =PROPER(TRIM(M86)) -> Ball | O86: 418.34 | P86: 5 | Q86: =IF(P86<1, 1, P86) -> 5 | R86: 5 | S86: =IF(OR(R86<0,R86>100),"invalid","Valid") -> Valid | T86: Cash | U86: =PROPER(TRIM(T86)) -> Cash | V86: Ada | W86: =PROPER(TRIM(V86)) -> Ada | X86: South | Y86: 1 | Z86: =IF(D86="", "Missing", "ok") -> ok | AA86: =(O86*Q86)*(1-R86/100) -> 1987.115
A87: T100087 | B87: 2025-08-26 | C87: C8641 | D87: John | E87: =PROPER(TRIM(D87)) -> John | F87: Female | G87: 46 | H87: =IF(AND(G87>18, G87<65), "Valid", "Invalid") -> Valid | I87: LAGOS | J87: =PROPER(TRIM(I87)) -> Lagos | K87: Beauty | L87: =PROPER(TRIM(K87)) -> Beauty | M87: Cream | N87: =PROPER(TRIM(M87)) -> Cream | O87: 214.36 | P87: -2 | Q87: =IF(P87<1, 1, P87) -> 1 | R87: 15 | S87: =IF(OR(R87<0,R87>100),"invalid","Valid") -> Valid | T87: POS | U87: =PROPER(TRIM(T87)) -> Pos | V87: Dan | W87: =PROPER(TRIM(V87)) -> Dan | X87: South | Z87: =IF(D87="", "Missing", "ok") -> ok | AA87: =(O87*Q87)*(1-R87/100) -> 182.206
A88: T100088 | B88: 2026-05-18 | C88: C1455 | D88: Grace | E88: =PROPER(TRIM(D88)) -> Grace | F88: Male | G88: 8 | H88: =IF(AND(G88>18, G88<65), "Valid", "Invalid") -> Invalid | I88: LAGOS | J88: =PROPER(TRIM(I88)) -> Lagos | K88: Beauty | L88: =PROPER(TRIM(K88)) -> Beauty | M88: Cream | N88: =PROPER(TRIM(M88)) -> Cream | O88: 57.71 | P88: -2 | Q88: =IF(P88<1, 1, P88) -> 1 | R88: -10 | S88: =IF(OR(R88<0,R88>100),"invalid","Valid") -> invalid | T88: Cash | U88: =PROPER(TRIM(T88)) -> Cash | V88: Ben | W88: =PROPER(TRIM(V88)) -> Ben | X88: West | Y88: 3 | Z88: =IF(D88="", "Missing", "ok") -> ok | AA88: =(O88*Q88)*(1-R88/100) -> 63.481
A89: T100089 | B89: 2025-11-17 | C89: C9562 | D89: Mary | E89: =PROPER(TRIM(D89)) -> Mary | F89: Male | G89: 8 | H89: =IF(AND(G89>18, G89<65), "Valid", "Invalid") -> Invalid | I89: Lagos | J89: =PROPER(TRIM(I89)) -> Lagos | K89: Sports | L89: =PROPER(TRIM(K89)) -> Sports | M89: Ball | N89: =PROPER(TRIM(M89)) -> Ball | O89: 370.55 | P89: -2 | Q89: =IF(P89<1, 1, P89) -> 1 | R89: 120 | S89: =IF(OR(R89<0,R89>100),"invalid","Valid") -> invalid | T89: Transfer | U89: =PROPER(TRIM(T89)) -> Transfer | V89: Ben | W89: =PROPER(TRIM(V89)) -> Ben | X89: West | Y89: 4 | Z89: =IF(D89="", "Missing", "ok") -> ok | AA89: =(O89*Q89)*(1-R89/100) -> -74.11
A90: T100090 | B90: 2025-07-11 | C90: C5842 | D90: Peter | E90: =PROPER(TRIM(D90)) -> Peter | F90: Male | G90: 8 | H90: =IF(AND(G90>18, G90<65), "Valid", "Invalid") -> Invalid | I90: Kano | J90: =PROPER(TRIM(I90)) -> Kano | K90: Sports | L90: =PROPER(TRIM(K90)) -> Sports | M90: Ball | N90: =PROPER(TRIM(M90)) -> Ball | O90: 331.75 | P90: -2 | Q90: =IF(P90<1, 1, P90) -> 1 | R90: 120 | S90: =IF(OR(R90<0,R90>100),"invalid","Valid") -> invalid | U90: =PROPER(TRIM(T90)) | V90: Ben | W90: =PROPER(TRIM(V90)) -> Ben | X90: East | Y90: 2 | Z90: =IF(D90="", "Missing", "ok") -> ok | AA90: =(O90*Q90)*(1-R90/100) -> -66.35
A91: T100091 | B91: 08/06/2025 | C91: C5213 | D91: Peter | E91: =PROPER(TRIM(D91)) -> Peter | F91: Male | G91: 130 | H91: =IF(AND(G91>18, G91<65), "Valid", "Invalid") -> Invalid | I91: Abuja | J91: =PROPER(TRIM(I91)) -> Abuja | K91: Fashion | L91: =PROPER(TRIM(K91)) -> Fashion | M91: Shirt | N91: =PROPER(TRIM(M91)) -> Shirt | O91: 265.26 | P91: -2 | Q91: =IF(P91<1, 1, P91) -> 1 | R91: 0 | S91: =IF(OR(R91<0,R91>100),"invalid","Valid") -> Valid | T91: POS | U91: =PROPER(TRIM(T91)) -> Pos | V91: Dan | W91: =PROPER(TRIM(V91)) -> Dan | X91: East | Y91: 5 | Z91: =IF(D91="", "Missing", "ok") -> ok | AA91: =(O91*Q91)*(1-R91/100) -> 265.26
A92: T100092 | B92: 2025-05-30 | C92: C5086 | D92: Mary | E92: =PROPER(TRIM(D92)) -> Mary | F92: Male | G92: 59 | H92: =IF(AND(G92>18, G92<65), "Valid", "Invalid") -> Valid | I92: lagos | J92: =PROPER(TRIM(I92)) -> Lagos | K92: Electronics | L92: =PROPER(TRIM(K92)) -> Electronics | M92: Phone | N92: =PROPER(TRIM(M92)) -> Phone | O92: 285.7 | P92: 4 | Q92: =IF(P92<1, 1, P92) -> 4 | R92: 0 | S92: =IF(OR(R92<0,R92>100),"invalid","Valid") -> Valid | U92: =PROPER(TRIM(T92)) | V92: Ben | W92: =PROPER(TRIM(V92)) -> Ben | X92: West | Y92: 5 | Z92: =IF(D92="", "Missing", "ok") -> ok | AA92: =(O92*Q92)*(1-R92/100) -> 1142.8
A93: T100093 | B93: 2025-11-24 | C93: C7239 | D93: Grace | E93: =PROPER(TRIM(D93)) -> Grace | F93: Female | G93: 130 | H93: =IF(AND(G93>18, G93<65), "Valid", "Invalid") -> Invalid | I93: Lagos | J93: =PROPER(TRIM(I93)) -> Lagos | K93: Groceries | L93: =PROPER(TRIM(K93)) -> Groceries | M93: Rice | N93: =PROPER(TRIM(M93)) -> Rice | O93: 109.04 | P93: 3 | Q93: =IF(P93<1, 1, P93) -> 3 | R93: 10 | S93: =IF(OR(R93<0,R93>100),"invalid","Valid") -> Valid | T93: Mobile Money | U93: =PROPER(TRIM(T93)) -> Mobile Money | V93: Ben | W93: =PROPER(TRIM(V93)) -> Ben | X93: North | Y93: 3 | Z93: =IF(D93="", "Missing", "ok") -> ok | AA93: =(O93*Q93)*(1-R93/100) -> 294.408
A94: T100094 | B94: 2025-06-11 | C94: C1489 | D94: Peter | E94: =PROPER(TRIM(D94)) -> Peter | F94: Male | G94: 130 | H94: =IF(AND(G94>18, G94<65), "Valid", "Invalid") -> Invalid | I94: LAGOS | J94: =PROPER(TRIM(I94)) -> Lagos | K94: Beauty | L94: =PROPER(TRIM(K94)) -> Beauty | M94: Cream | N94: =PROPER(TRIM(M94)) -> Cream | O94: 322.57 | P94: 8 | Q94: =IF(P94<1, 1, P94) -> 8 | R94: 10 | S94: =IF(OR(R94<0,R94>100),"invalid","Valid") -> Valid | T94: Cash | U94: =PROPER(TRIM(T94)) -> Cash | V94: Dan | W94: =PROPER(TRIM(V94)) -> Dan | X94: West | Y94: 5 | Z94: =IF(D94="", "Missing", "ok") -> ok | AA94: =(O94*Q94)*(1-R94/100) -> 2322.504
A95: T100095 | B95: 2025-05-30 | C95: C4488 | D95: David | E95: =PROPER(TRIM(D95)) -> David | F95: Male | G95: 130 | H95: =IF(AND(G95>18, G95<65), "Valid", "Invalid") -> Invalid | I95: Abuja | J95: =PROPER(TRIM(I95)) -> Abuja | K95: Sports | L95: =PROPER(TRIM(K95)) -> Sports | M95: Ball | N95: =PROPER(TRIM(M95)) -> Ball | O95: 350.62 | P95: -2 | Q95: =IF(P95<1, 1, P95) -> 1 | R95: 15 | S95: =IF(OR(R95<0,R95>100),"invalid","Valid") -> Valid | U95: =PROPER(TRIM(T95)) | V95: Ben | W95: =PROPER(TRIM(V95)) -> Ben | X95: East | Y95: 2 | Z95: =IF(D95="", "Missing", "ok") -> ok | AA95: =(O95*Q95)*(1-R95/100) -> 298.027
A96: T100096 | B96: 2026-01-21 | C96: C9757 | D96: John | E96: =PROPER(TRIM(D96)) -> John | F96: Male | G96: 43 | H96: =IF(AND(G96>18, G96<65), "Valid", "Invalid") -> Valid | I96: Kano | J96: =PROPER(TRIM(I96)) -> Kano | K96: Groceries | L96: =PROPER(TRIM(K96)) -> Groceries | M96: Rice | N96: =PROPER(TRIM(M96)) -> Rice | O96: 499.74 | P96: 1 | Q96: =IF(P96<1, 1, P96) -> 1 | R96: 10 | S96: =IF(OR(R96<0,R96>100),"invalid","Valid") -> Valid | U96: =PROPER(TRIM(T96)) | V96: Dan | W96: =PROPER(TRIM(V96)) -> Dan | X96: East | Y96: 1 | Z96: =IF(D96="", "Missing", "ok") -> ok | AA96: =(O96*Q96)*(1-R96/100) -> 449.766
A97: T100097 | B97: 2025-03-19 | C97: C9462 | D97: David | E97: =PROPER(TRIM(D97)) -> David | F97: Female | G97: 29 | H97: =IF(AND(G97>18, G97<65), "Valid", "Invalid") -> Valid | I97: lagos | J97: =PROPER(TRIM(I97)) -> Lagos | K97: Home | L97: =PROPER(TRIM(K97)) -> Home | M97: Chair | N97: =PROPER(TRIM(M97)) -> Chair | O97: 304.02 | P97: 6 | Q97: =IF(P97<1, 1, P97) -> 6 | R97: 120 | S97: =IF(OR(R97<0,R97>100),"invalid","Valid") -> invalid | T97: Mobile Money | U97: =PROPER(TRIM(T97)) -> Mobile Money | V97: Dan | W97: =PROPER(TRIM(V97)) -> Dan | X97: South | Y97: 2 | Z97: =IF(D97="", "Missing", "ok") -> ok | AA97: =(O97*Q97)*(1-R97/100) -> -364.824
A98: T100098 | B98: 17/07/2025 | C98: C4611 | D98: David | E98: =PROPER(TRIM(D98)) -> David | F98: Female | G98: 25 | H98: =IF(AND(G98>18, G98<65), "Valid", "Invalid") -> Valid | I98: PH | J98: =PROPER(TRIM(I98)) -> Ph | K98: Home | L98: =PROPER(TRIM(K98)) -> Home | M98: Chair | N98: =PROPER(TRIM(M98)) -> Chair | O98: 137.31 | P98: 3 | Q98: =IF(P98<1, 1, P98) -> 3 | R98: 10 | S98: =IF(OR(R98<0,R98>100),"invalid","Valid") -> Valid | T98: Cash | U98: =PROPER(TRIM(T98)) -> Cash | V98: Ben | W98: =PROPER(TRIM(V98)) -> Ben | X98: West | Y98: 5 | Z98: =IF(D98="", "Missing", "ok") -> ok | AA98: =(O98*Q98)*(1-R98/100) -> 370.737
A99: T100099 | B99: 2025-12-03 | C99: C6147 | D99: Grace | E99: =PROPER(TRIM(D99)) -> Grace | F99: Female | G99: 8 | H99: =IF(AND(G99>18, G99<65), "Valid", "Invalid") -> Invalid | I99: lagos | J99: =PROPER(TRIM(I99)) -> Lagos | K99: groceris | L99: =PROPER(TRIM(K99)) -> Groceris | M99: Rice | N99: =PROPER(TRIM(M99)) -> Rice | O99: 353.95 | P99: -2 | Q99: =IF(P99<1, 1, P99) -> 1 | R99: 15 | S99: =IF(OR(R99<0,R99>100),"invalid","Valid") -> Valid | T99: Cash | U99: =PROPER(TRIM(T99)) -> Cash | V99: Ben | W99: =PROPER(TRIM(V99)) -> Ben | X99: North | Y99: 5 | Z99: =IF(D99="", "Missing", "ok") -> ok | AA99: =(O99*Q99)*(1-R99/100) -> 300.8575
A100: T100100 | B100: 2026-04-21 | C100: C7371 | D100: Grace | E100: =PROPER(TRIM(D100)) -> Grace | F100: Male | G100: 34 | H100: =IF(AND(G100>18, G100<65), "Valid", "Invalid") -> Valid | I100: LAGOS | J100: =PROPER(TRIM(I100)) -> Lagos | K100: groceris | L100: =PROPER(TRIM(K100)) -> Groceris | M100: Rice | N100: =PROPER(TRIM(M100)) -> Rice | O100: 218.73 | P100: 10 | Q100: =IF(P100<1, 1, P100) -> 10 | R100: 0 | S100: =IF(OR(R100<0,R100>100),"invalid","Valid") -> Valid | T100: POS | U100: =PROPER(TRIM(T100)) -> Pos | V100: Ada | W100: =PROPER(TRIM(V100)) -> Ada | X100: East | Y100: 5 | Z100: =IF(D100="", "Missing", "ok") -> ok | AA100: =(O100*Q100)*(1-R100/100) -> 2187.3
A101: T100101 | B101: 2025-08-23 | C101: C7489 | D101: James | E101: =PROPER(TRIM(D101)) -> James | F101: Male | G101: 130 | H101: =IF(AND(G101>18, G101<65), "Valid", "Invalid") -> Invalid | I101: Enugu | J101: =PROPER(TRIM(I101)) -> Enugu | K101: Groceries | L101: =PROPER(TRIM(K101)) -> Groceries | M101: Rice | N101: =PROPER(TRIM(M101)) -> Rice | O101: 225.05 | P101: -2 | Q101: =IF(P101<1, 1, P101) -> 1 | R101: 120 | S101: =IF(OR(R101<0,R101>100),"invalid","Valid") -> invalid | T101: Mobile Money | U101: =PROPER(TRIM(T101)) -> Mobile Money | V101: Ada | W101: =PROPER(TRIM(V101)) -> Ada | X101: East | Y101: 2 | Z101: =IF(D101="", "Missing", "ok") -> ok | AA101: =(O101*Q101)*(1-R101/100) -> -45.01
A102: T100102 | B102: 2025-11-28 | C102: C9515 | D102: Peter | E102: =PROPER(TRIM(D102)) -> Peter | F102: Male | G102: 130 | H102: =IF(AND(G102>18, G102<65), "Valid", "Invalid") -> Invalid | I102: LAGOS | J102: =PROPER(TRIM(I102)) -> Lagos | K102: Groceries | L102: =PROPER(TRIM(K102)) -> Groceries | M102: Rice | N102: =PROPER(TRIM(M102)) -> Rice | O102: 256.71 | P102: 6 | Q102: =IF(P102<1, 1, P102) -> 6 | R102: 0 | S102: =IF(OR(R102<0,R102>100),"invalid","Valid") -> Valid | T102: POS | U102: =PROPER(TRIM(T102)) -> Pos | V102: Ben | W102: =PROPER(TRIM(V102)) -> Ben | X102: East | Y102: 4 | Z102: =IF(D102="", "Missing", "ok") -> ok | AA102: =(O102*Q102)*(1-R102/100) -> 1540.26
A103: T100103 | B103: 2025-05-26 | C103: C3710 | D103: Peter | E103: =PROPER(TRIM(D103)) -> Peter | F103: Female | G103: 130 | H103: =IF(AND(G103>18, G103<65), "Valid", "Invalid") -> Invalid | I103: Enugu | J103: =PROPER(TRIM(I103)) -> Enugu | K103: Groceries | L103: =PROPER(TRIM(K103)) -> Groceries | M103: Rice | N103: =PROPER(TRIM(M103)) -> Rice | O103: 245.32 | P103: 4 | Q103: =IF(P103<1, 1, P103) -> 4 | R103: 15 | S103: =IF(OR(R103<0,R103>100),"invalid","Valid") -> Valid | T103: POS | U103: =PROPER(TRIM(T103)) -> Pos | V103: Ada | W103: =PROPER(TRIM(V103)) -> Ada | X103: East | Z103: =IF(D103="", "Missing", "ok") -> ok | AA103: =(O103*Q103)*(1-R103/100) -> 834.088
...

Sheet EDA
A1: KPI | B1: Value
A2: Total_Revenue | B2: =SUM('WORKING DATA'!Q:Q) -> 3944
A3: Number_of_Transactions | B3: =COUNTA('WORKING DATA'!A:A)-1 -> 1196
A4: Ave._Transaction | B4: =AVERAGE('WORKING DATA'!Q:Q) -> 3.2976589
A5: Highest_Sale | B5: =MAX('WORKING DATA'!Q:Q) -> 42
A6: Lowest_Sale | B6: =MIN('WORKING DATA'!Q:Q) -> 1
A9: Product_Category | B9: Revenue
A10: Electronic | B10: =SUMIF('WORKING DATA'!K:K,A10,'WORKING DATA'!AA:AA) -> 0
A11: Groceries | B11: =SUMIF('WORKING DATA'!K:K,A11,'WORKING DATA'!AA:AA) -> 88690.391
A12: Fashion | B12: =SUMIF('WORKING DATA'!K:K,A12,'WORKING DATA'!AA:AA) -> 118710.26
A13: Home | B13: =SUMIF('WORKING DATA'!K:K,A13,'WORKING DATA'!AA:AA) -> 83554.633
A14: Beauty | B14: =SUMIF('WORKING DATA'!K:K,A14,'WORKING DATA'!AA:AA) -> 109063.33
A15: Sports | B15: =SUMIF('WORKING DATA'!K:K,A15,'WORKING DATA'!AA:AA) -> 112686.8
A18: Branch | B18: Revenue
A19: North | B19: =SUMIF('WORKING DATA'!X:X,A18,'WORKING DATA'!AA:AA) -> 0
A20: South | B20: =SUMIF('WORKING DATA'!X:X,A19,'WORKING DATA'!AA:AA) -> 209640.86
A21: West | B21: =SUMIF('WORKING DATA'!X:X,A20,'WORKING DATA'!AA:AA) -> 168416.76
A22: East | B22: =SUMIF('WORKING DATA'!X:X,A21,'WORKING DATA'!AA:AA) -> 195085.64
A25: City | B25: Revenue
A26: Lagos | B26: =SUMIF('WORKING DATA'!I:I, A26, 'WORKING DATA'!AA:AA) -> 308160.4
A27: Abuja | B27: =SUMIF('WORKING DATA'!I:I, A27, 'WORKING DATA'!AA:AA) -> 138012.53
A28: Kano | B28: =SUMIF('WORKING DATA'!I:I, A28, 'WORKING DATA'!AA:AA) -> 107389.43
A29: Enugu | B29: =SUMIF('WORKING DATA'!I:I, A29, 'WORKING DATA'!AA:AA) -> 107638.82
A30: Ph | B30: =SUMIF('WORKING DATA'!I:I, A30, 'WORKING DATA'!AA:AA) -> 104867.74
